{"D:\\Application\\entry\\src\\main\\config.json":{"hashValue":"b44c59e9085a91e8ded03e91b38e931a","name":"config.json","path":"D:\\Application\\entry\\src\\main\\config.json","type":"file","isSymbolicLink":false,"fileMetaData":{"size":1427,"lastModifiedTime":1688461234438}},"D:\\Application\\entry\\.preview\\default\\intermediates\\merge_profile\\default\\config.json":{"hashValue":"bffc7a1e988572b967afbdc5a005f27a","name":"config.json","path":"D:\\Application\\entry\\.preview\\default\\intermediates\\merge_profile\\default\\config.json","type":"file","isSymbolicLink":false,"fileMetaData":{"size":1267,"lastModifiedTime":1688443328513}},"D:\\Application\\entry\\.preview\\default\\intermediates\\manifest\\default":{"hashValue":"06934368403596ff1cd03ff0592d5cec","name":"default","path":"D:\\Application\\entry\\.preview\\default\\intermediates\\manifest\\default","type":"directory","isSymbolicLink":false,"children":[{"hashValue":"9b0c25999ea416afd8fdf0b95fe60c94","name":"MainAbility","path":"D:\\Application\\entry\\.preview\\default\\intermediates\\manifest\\default\\MainAbility","type":"directory","isSymbolicLink":false,"children":[{"hashValue":"b14c0f1ac8cb7eb6b1b8f53ae6f45f49","name":"manifest.json","path":"D:\\Application\\entry\\.preview\\default\\intermediates\\manifest\\default\\MainAbility\\manifest.json","type":"file","isSymbolicLink":false,"fileMetaData":{"size":245,"lastModifiedTime":1688443328522}}]}]},"D:\\Application\\entry\\build-profile.json5":{"hashValue":"0250bea7bda88ff41bd2cd4ca9ce3d9c","name":"build-profile.json5","path":"D:\\Application\\entry\\build-profile.json5","type":"file","isSymbolicLink":false,"fileMetaData":{"size":779,"lastModifiedTime":1688461474729}},"D:\\Application\\entry\\.preview\\default\\intermediates\\process_profile\\default\\config.json":{"hashValue":"ef041de44dce070055d1c3284ef36f59","name":"config.json","path":"D:\\Application\\entry\\.preview\\default\\intermediates\\process_profile\\default\\config.json","type":"file","isSymbolicLink":false,"fileMetaData":{"size":955,"lastModifiedTime":1688443328650}},"D:\\Application\\entry\\.preview\\default\\intermediates\\loader\\default\\MainAbility\\loader.json":{"hashValue":"bfb1ff8e7d84008b2e022201543659c3","name":"loader.json","path":"D:\\Application\\entry\\.preview\\default\\intermediates\\loader\\default\\MainAbility\\loader.json","type":"file","isSymbolicLink":false,"fileMetaData":{"size":142,"lastModifiedTime":1688443328654}},"D:\\Application\\entry\\src\\main\\resources":{"hashValue":"9217eee9573c4e9c1f9244c7d84c16ad","name":"resources","path":"D:\\Application\\entry\\src\\main\\resources","type":"directory","isSymbolicLink":false,"children":[{"hashValue":"9fe98dfd7e44d950386c43b7fa76c7a7","name":"base","path":"D:\\Application\\entry\\src\\main\\resources\\base","type":"directory","isSymbolicLink":false,"children":[{"hashValue":"a891ddf4874509ae1adfffe496d377e0","name":"element","path":"D:\\Application\\entry\\src\\main\\resources\\base\\element","type":"directory","isSymbolicLink":false,"children":[{"hashValue":"8a2eeaefa7e544988753646ee8e3e052","name":"color.json","path":"D:\\Application\\entry\\src\\main\\resources\\base\\element\\color.json","type":"file","isSymbolicLink":false,"fileMetaData":{"size":105,"lastModifiedTime":1688438694158}},{"hashValue":"a4f154356848422e3309b1343c7160d3","name":"string.json","path":"D:\\Application\\entry\\src\\main\\resources\\base\\element\\string.json","type":"file","isSymbolicLink":false,"fileMetaData":{"size":245,"lastModifiedTime":1688438695436}}]},{"hashValue":"5be04b5645efd573c74f54ada5a9fac8","name":"media","path":"D:\\Application\\entry\\src\\main\\resources\\base\\media","type":"directory","isSymbolicLink":false,"children":[{"hashValue":"a51f723ed916a0b72c691fc7594bbd1e","name":"icon.png","path":"D:\\Application\\entry\\src\\main\\resources\\base\\media\\icon.png","type":"file","isSymbolicLink":false,"fileMetaData":{"size":6790,"lastModifiedTime":1688438694167}}]}]},{"hashValue":"b63ffbe891fa4e0e9321f22d09e85ca1","name":"en_US","path":"D:\\Application\\entry\\src\\main\\resources\\en_US","type":"directory","isSymbolicLink":false,"children":[{"hashValue":"6d4d95b2fb589429748b362e58e77976","name":"element","path":"D:\\Application\\entry\\src\\main\\resources\\en_US\\element","type":"directory","isSymbolicLink":false,"children":[{"hashValue":"ff9e5a5ba49489e968eccc231333e319","name":"string.json","path":"D:\\Application\\entry\\src\\main\\resources\\en_US\\element\\string.json","type":"file","isSymbolicLink":false,"fileMetaData":{"size":245,"lastModifiedTime":1688438695426}}]}]},{"hashValue":"","name":"rawfile","path":"D:\\Application\\entry\\src\\main\\resources\\rawfile","type":"directory","isSymbolicLink":false,"children":[]},{"hashValue":"01b2259830566aa88ac8e3e28aab6835","name":"zh_CN","path":"D:\\Application\\entry\\src\\main\\resources\\zh_CN","type":"directory","isSymbolicLink":false,"children":[{"hashValue":"4b8f3f66a6ab055d1423fe8e0d621b34","name":"element","path":"D:\\Application\\entry\\src\\main\\resources\\zh_CN\\element","type":"directory","isSymbolicLink":false,"children":[{"hashValue":"d965e8db79a5102c0806880fcba0768d","name":"string.json","path":"D:\\Application\\entry\\src\\main\\resources\\zh_CN\\element\\string.json","type":"file","isSymbolicLink":false,"fileMetaData":{"size":239,"lastModifiedTime":1688438695453}}]}]}]},"D:\\Application\\entry\\.preview\\default\\intermediates\\res\\default":{"hashValue":"cd96fd760945b6015052ce22e2b1c0ab","name":"default","path":"D:\\Application\\entry\\.preview\\default\\intermediates\\res\\default","type":"directory","isSymbolicLink":false,"children":[{"hashValue":"8b8005df1c2d57d03efd240b648bede5","name":"config.json","path":"D:\\Application\\entry\\.preview\\default\\intermediates\\res\\default\\config.json","type":"file","isSymbolicLink":false,"fileMetaData":{"size":2334,"lastModifiedTime":1688443328842}},{"hashValue":"667bcc3e5551383e349535fd6a68daff","name":"module_compiled","path":"D:\\Application\\entry\\.preview\\default\\intermediates\\res\\default\\module_compiled","type":"directory","isSymbolicLink":false,"children":[{"hashValue":"a82206183557f85e47e733cde0e39b30","name":"11342993839070767880","path":"D:\\Application\\entry\\.preview\\default\\intermediates\\res\\default\\module_compiled\\11342993839070767880","type":"file","isSymbolicLink":false,"fileMetaData":{"size":121,"lastModifiedTime":1688443328775}},{"hashValue":"3ec74b91b1582c327a0cd77c247fe122","name":"14011687016997442750","path":"D:\\Application\\entry\\.preview\\default\\intermediates\\res\\default\\module_compiled\\14011687016997442750","type":"file","isSymbolicLink":false,"fileMetaData":{"size":402,"lastModifiedTime":1688443328777}},{"hashValue":"87260bacabbb7f73c32b8dc2f8a67a2a","name":"619418883896271835","path":"D:\\Application\\entry\\.preview\\default\\intermediates\\res\\default\\module_compiled\\619418883896271835","type":"file","isSymbolicLink":false,"fileMetaData":{"size":154,"lastModifiedTime":1688443328776}},{"hashValue":"56ac6ca53ed40dec98a6bfedfd90d08c","name":"8590548873808170899","path":"D:\\Application\\entry\\.preview\\default\\intermediates\\res\\default\\module_compiled\\8590548873808170899","type":"file","isSymbolicLink":false,"fileMetaData":{"size":408,"lastModifiedTime":1688443328777}},{"hashValue":"23ef9b5f095713c46616ab15a0e53815","name":"9405056907713820483","path":"D:\\Application\\entry\\.preview\\default\\intermediates\\res\\default\\module_compiled\\9405056907713820483","type":"file","isSymbolicLink":false,"fileMetaData":{"size":354,"lastModifiedTime":1688443328775}}]},{"hashValue":"f5e7bfa4caf70e7b7dc22edbd266fec4","name":"resources.index","path":"D:\\Application\\entry\\.preview\\default\\intermediates\\res\\default\\resources.index","type":"file","isSymbolicLink":false,"fileMetaData":{"size":835,"lastModifiedTime":1688443328841}},{"hashValue":"add121562a84b2cc56a66556930ceefb","name":"ResourceTable.txt","path":"D:\\Application\\entry\\.preview\\default\\intermediates\\res\\default\\ResourceTable.txt","type":"file","isSymbolicLink":false,"fileMetaData":{"size":163,"lastModifiedTime":1688443328843}}]},"D:\\Application\\entry\\.preview\\default\\cache\\default\\r\\ResourceTable.h":{"hashValue":"8b7691622dded902208024c6330ce4bb","name":"ResourceTable.h","path":"D:\\Application\\entry\\.preview\\default\\cache\\default\\r\\ResourceTable.h","type":"file","isSymbolicLink":false,"fileMetaData":{"size":954,"lastModifiedTime":1688443328842}},"D:\\Application\\entry\\.preview\\default\\cache\\default\\r":{"hashValue":"af1f5421d1b642f64f82fe9b6d16c72f","name":"r","path":"D:\\Application\\entry\\.preview\\default\\cache\\default\\r","type":"directory","isSymbolicLink":false,"children":[{"hashValue":"8b7691622dded902208024c6330ce4bb","name":"ResourceTable.h","path":"D:\\Application\\entry\\.preview\\default\\cache\\default\\r\\ResourceTable.h","type":"file","isSymbolicLink":false,"fileMetaData":{"size":954,"lastModifiedTime":1688443328842}}]},"D:\\Application\\entry\\build\\default\\intermediates\\hap_metadata\\default\\output_metadata.json":{"hashValue":"7e942ca09f16fee3cc1fe286180e71b9","name":"output_metadata.json","path":"D:\\Application\\entry\\build\\default\\intermediates\\hap_metadata\\default\\output_metadata.json","type":"file","isSymbolicLink":false,"fileMetaData":{"size":92,"lastModifiedTime":1688461726810}},"D:\\Application\\entry\\build\\default\\intermediates\\merge_profile\\default\\config.json":{"hashValue":"49e6907f4989b10a0449db7e17ea3eeb","name":"config.json","path":"D:\\Application\\entry\\build\\default\\intermediates\\merge_profile\\default\\config.json","type":"file","isSymbolicLink":false,"fileMetaData":{"size":1285,"lastModifiedTime":1688461726816}},"D:\\Application\\entry\\build\\default\\intermediates\\manifest\\default":{"hashValue":"df38db319c7e7fcb9ef5f602e5ffa0d2","name":"default","path":"D:\\Application\\entry\\build\\default\\intermediates\\manifest\\default","type":"directory","isSymbolicLink":false,"children":[{"hashValue":"706cce50bbcb229a25b9e639e8c183e7","name":"MainAbility","path":"D:\\Application\\entry\\build\\default\\intermediates\\manifest\\default\\MainAbility","type":"directory","isSymbolicLink":false,"children":[{"hashValue":"24d7c635eb8f3acb9ae0d837fbafedb7","name":"manifest.json","path":"D:\\Application\\entry\\build\\default\\intermediates\\manifest\\default\\MainAbility\\manifest.json","type":"file","isSymbolicLink":false,"fileMetaData":{"size":256,"lastModifiedTime":1688461726840}}]}]},"D:\\Application\\entry\\build\\default\\outputs\\default\\pack.info":{"hashValue":"0c25b9e2d486f20dabfd7df0e3bd0584","name":"pack.info","path":"D:\\Application\\entry\\build\\default\\outputs\\default\\pack.info","type":"file","isSymbolicLink":false,"fileMetaData":{"size":569,"lastModifiedTime":1688461726842}},"D:\\Application\\entry\\build\\default\\intermediates\\process_profile\\default\\config.json":{"hashValue":"2006af79acf4a0b78378325e7c14a13a","name":"config.json","path":"D:\\Application\\entry\\build\\default\\intermediates\\process_profile\\default\\config.json","type":"file","isSymbolicLink":false,"fileMetaData":{"size":973,"lastModifiedTime":1688461726988}},"D:\\Application\\entry\\build\\default\\intermediates\\loader\\default\\MainAbility\\loader.json":{"hashValue":"37860bea527d21b645bde9ca4a05b75b","name":"loader.json","path":"D:\\Application\\entry\\build\\default\\intermediates\\loader\\default\\MainAbility\\loader.json","type":"file","isSymbolicLink":false,"fileMetaData":{"size":142,"lastModifiedTime":1688461726992}},"D:\\Application\\entry\\build\\default\\intermediates\\res\\default\\resConfig.json":{"hashValue":"959cbf000480ee6ae9eff78ef584c90b","name":"resConfig.json","path":"D:\\Application\\entry\\build\\default\\intermediates\\res\\default\\resConfig.json","type":"file","isSymbolicLink":false,"fileMetaData":{"size":441,"lastModifiedTime":1688461726995}},"D:\\Application\\entry\\build\\default\\intermediates\\libs\\default":{"hashValue":"","name":"default","path":"D:\\Application\\entry\\build\\default\\intermediates\\libs\\default","type":"directory","isSymbolicLink":false,"children":[]},"D:\\Application\\entry\\build\\default\\intermediates\\res\\default":{"hashValue":"84c671da11dc947779b63413044f6e12","name":"default","path":"D:\\Application\\entry\\build\\default\\intermediates\\res\\default","type":"directory","isSymbolicLink":false,"children":[{"hashValue":"7ab94cad0ca9d20eacef971b8c844fad","name":"config.json","path":"D:\\Application\\entry\\build\\default\\intermediates\\res\\default\\config.json","type":"file","isSymbolicLink":false,"fileMetaData":{"size":2352,"lastModifiedTime":1688461727095}},{"hashValue":"959cbf000480ee6ae9eff78ef584c90b","name":"resConfig.json","path":"D:\\Application\\entry\\build\\default\\intermediates\\res\\default\\resConfig.json","type":"file","isSymbolicLink":false,"fileMetaData":{"size":441,"lastModifiedTime":1688461726995}},{"hashValue":"c384355f69733ff77f925512574987bd","name":"resources","path":"D:\\Application\\entry\\build\\default\\intermediates\\res\\default\\resources","type":"directory","isSymbolicLink":false,"children":[{"hashValue":"a5375fa2da5841fa53b639da938ade77","name":"base","path":"D:\\Application\\entry\\build\\default\\intermediates\\res\\default\\resources\\base","type":"directory","isSymbolicLink":false,"children":[{"hashValue":"5be04b5645efd573c74f54ada5a9fac8","name":"media","path":"D:\\Application\\entry\\build\\default\\intermediates\\res\\default\\resources\\base\\media","type":"directory","isSymbolicLink":false,"children":[{"hashValue":"a51f723ed916a0b72c691fc7594bbd1e","name":"icon.png","path":"D:\\Application\\entry\\build\\default\\intermediates\\res\\default\\resources\\base\\media\\icon.png","type":"file","isSymbolicLink":false,"fileMetaData":{"size":6790,"lastModifiedTime":1688438694167}}]}]},{"hashValue":"","name":"rawfile","path":"D:\\Application\\entry\\build\\default\\intermediates\\res\\default\\resources\\rawfile","type":"directory","isSymbolicLink":false,"children":[]}]},{"hashValue":"dede9f3982ecc1e0f1d89fb3c7574651","name":"resources.index","path":"D:\\Application\\entry\\build\\default\\intermediates\\res\\default\\resources.index","type":"file","isSymbolicLink":false,"fileMetaData":{"size":811,"lastModifiedTime":1688461727095}},{"hashValue":"8c118bd17be672ac1542994c1982912e","name":"ResourceTable.txt","path":"D:\\Application\\entry\\build\\default\\intermediates\\res\\default\\ResourceTable.txt","type":"file","isSymbolicLink":false,"fileMetaData":{"size":163,"lastModifiedTime":1688461727094}}]},"D:\\Application\\entry\\build\\default\\cache\\default\\r\\ResourceTable.h":{"hashValue":"c974f78d9f4a372feed83245f1c1eb4e","name":"ResourceTable.h","path":"D:\\Application\\entry\\build\\default\\cache\\default\\r\\ResourceTable.h","type":"file","isSymbolicLink":false,"fileMetaData":{"size":954,"lastModifiedTime":1688461727093}},"D:\\Application\\entry\\build\\default\\cache\\default\\r":{"hashValue":"20c9b0874da4ecb226f15d855c9b34d7","name":"r","path":"D:\\Application\\entry\\build\\default\\cache\\default\\r","type":"directory","isSymbolicLink":false,"children":[{"hashValue":"c974f78d9f4a372feed83245f1c1eb4e","name":"ResourceTable.h","path":"D:\\Application\\entry\\build\\default\\cache\\default\\r\\ResourceTable.h","type":"file","isSymbolicLink":false,"fileMetaData":{"size":954,"lastModifiedTime":1688461727093}}]},"D:\\Application\\entry\\build\\default\\intermediates\\loader\\default":{"hashValue":"b4d7a7c2dac3b4d5e90db387819740c5","name":"default","path":"D:\\Application\\entry\\build\\default\\intermediates\\loader\\default","type":"directory","isSymbolicLink":false,"children":[{"hashValue":"4355ee235b3b1ac1f596019d073b8d1f","name":"MainAbility","path":"D:\\Application\\entry\\build\\default\\intermediates\\loader\\default\\MainAbility","type":"directory","isSymbolicLink":false,"children":[{"hashValue":"37860bea527d21b645bde9ca4a05b75b","name":"loader.json","path":"D:\\Application\\entry\\build\\default\\intermediates\\loader\\default\\MainAbility\\loader.json","type":"file","isSymbolicLink":false,"fileMetaData":{"size":142,"lastModifiedTime":1688461726992}}]}]},"D:\\Application\\entry\\build\\default\\intermediates\\res\\default\\ResourceTable.txt":{"hashValue":"8c118bd17be672ac1542994c1982912e","name":"ResourceTable.txt","path":"D:\\Application\\entry\\build\\default\\intermediates\\res\\default\\ResourceTable.txt","type":"file","isSymbolicLink":false,"fileMetaData":{"size":163,"lastModifiedTime":1688461727094}},"D:\\Application\\entry\\build\\default\\intermediates\\loader_out\\default\\ets":{"hashValue":"","name":"emptyroot","path":"","type":"unknown","isSymbolicLink":false,"children":[]},"D:\\Application\\entry\\src\\main\\js":{"hashValue":"6b7fea04b38e843e01e24b990d85a948","name":"js","path":"D:\\Application\\entry\\src\\main\\js","type":"directory","isSymbolicLink":false,"children":[{"hashValue":"b01cc30eac54b0a51828a11f73aea3a0","name":"MainAbility","path":"D:\\Application\\entry\\src\\main\\js\\MainAbility","type":"directory","isSymbolicLink":false,"children":[{"hashValue":"fc8564380308f036bfa1eeb72e768c53","name":"app.js","path":"D:\\Application\\entry\\src\\main\\js\\MainAbility\\app.js","type":"file","isSymbolicLink":false,"fileMetaData":{"size":864,"lastModifiedTime":1688461418561}},{"hashValue":"33ab1fe872fcc47d9e8ba0f808b45786","name":"i18n","path":"D:\\Application\\entry\\src\\main\\js\\MainAbility\\i18n","type":"directory","isSymbolicLink":false,"children":[{"hashValue":"a0c3282eaae3f50f3c80825224ce8b8f","name":"en-US.json","path":"D:\\Application\\entry\\src\\main\\js\\MainAbility\\i18n\\en-US.json","type":"file","isSymbolicLink":false,"fileMetaData":{"size":83,"lastModifiedTime":1688438694216}},{"hashValue":"de5770586653f63b37bb7a3b8c62eaaf","name":"zh-CN.json","path":"D:\\Application\\entry\\src\\main\\js\\MainAbility\\i18n\\zh-CN.json","type":"file","isSymbolicLink":false,"fileMetaData":{"size":85,"lastModifiedTime":1688438694222}}]},{"hashValue":"0a23d69e73771693c0459f39304719f8","name":"pages","path":"D:\\Application\\entry\\src\\main\\js\\MainAbility\\pages","type":"directory","isSymbolicLink":false,"children":[{"hashValue":"ba23a18efa98b59d5d6fda68a6287a88","name":"index","path":"D:\\Application\\entry\\src\\main\\js\\MainAbility\\pages\\index","type":"directory","isSymbolicLink":false,"children":[{"hashValue":"8c59c6fac92c150c6a85fb9006f75c91","name":"index.css","path":"D:\\Application\\entry\\src\\main\\js\\MainAbility\\pages\\index\\index.css","type":"file","isSymbolicLink":false,"fileMetaData":{"size":499,"lastModifiedTime":1688438694232}},{"hashValue":"0f81dd39050e0c0d54f23b037a9b2949","name":"index.hml","path":"D:\\Application\\entry\\src\\main\\js\\MainAbility\\pages\\index\\index.hml","type":"file","isSymbolicLink":false,"fileMetaData":{"size":114,"lastModifiedTime":1688438694238}},{"hashValue":"f186951af2f310461f9ed5b0784a6ac3","name":"index.js","path":"D:\\Application\\entry\\src\\main\\js\\MainAbility\\pages\\index\\index.js","type":"file","isSymbolicLink":false,"fileMetaData":{"size":735,"lastModifiedTime":1688461407634}}]}]}]}]},"D:\\Application\\entry\\build\\default\\intermediates\\loader_out\\default\\js":{"hashValue":"fbd811ecd0d64ec6352365f767b0eb39","name":"js","path":"D:\\Application\\entry\\build\\default\\intermediates\\loader_out\\default\\js","type":"directory","isSymbolicLink":false,"children":[{"hashValue":"764ac8c318367313e9015a8c4c3db646","name":"MainAbility","path":"D:\\Application\\entry\\build\\default\\intermediates\\loader_out\\default\\js\\MainAbility","type":"directory","isSymbolicLink":false,"children":[{"hashValue":"210ad45d91b279078f40c27953edea11","name":"app.abc","path":"D:\\Application\\entry\\build\\default\\intermediates\\loader_out\\default\\js\\MainAbility\\app.abc","type":"file","isSymbolicLink":false,"fileMetaData":{"size":28732,"lastModifiedTime":1688461729423}},{"hashValue":"c8f40671af0594f5e5c7e07c7b449ef5","name":"app.js","path":"D:\\Application\\entry\\build\\default\\intermediates\\loader_out\\default\\js\\MainAbility\\app.js","type":"file","isSymbolicLink":false,"fileMetaData":{"size":13542,"lastModifiedTime":1688461729382}},{"hashValue":"ea3bad378ec1bb65fc0a232a928b9f7e","name":"app.js.map","path":"D:\\Application\\entry\\build\\default\\intermediates\\loader_out\\default\\js\\MainAbility\\app.js.map","type":"file","isSymbolicLink":false,"fileMetaData":{"size":1871,"lastModifiedTime":1688461729348}},{"hashValue":"c5b83b17be069c7889c1adefc8dbd8c7","name":"i18n","path":"D:\\Application\\entry\\build\\default\\intermediates\\loader_out\\default\\js\\MainAbility\\i18n","type":"directory","isSymbolicLink":false,"children":[{"hashValue":"e43635dd195fb1345adcd9d64e64e23a","name":"en-US.json","path":"D:\\Application\\entry\\build\\default\\intermediates\\loader_out\\default\\js\\MainAbility\\i18n\\en-US.json","type":"file","isSymbolicLink":false,"fileMetaData":{"size":83,"lastModifiedTime":1688461729348}},{"hashValue":"96dbe78810cdcafad74a262dc861b1fb","name":"zh-CN.json","path":"D:\\Application\\entry\\build\\default\\intermediates\\loader_out\\default\\js\\MainAbility\\i18n\\zh-CN.json","type":"file","isSymbolicLink":false,"fileMetaData":{"size":85,"lastModifiedTime":1688461729348}}]},{"hashValue":"539680930be7c502d85bbdeffe90fbd0","name":"manifest.json","path":"D:\\Application\\entry\\build\\default\\intermediates\\loader_out\\default\\js\\MainAbility\\manifest.json","type":"file","isSymbolicLink":false,"fileMetaData":{"size":256,"lastModifiedTime":1688461729388}},{"hashValue":"d2aa3bb95501998d008caa784a446372","name":"pages","path":"D:\\Application\\entry\\build\\default\\intermediates\\loader_out\\default\\js\\MainAbility\\pages","type":"directory","isSymbolicLink":false,"children":[{"hashValue":"f4f832c02b43bd5b45e29696aa0fe74d","name":"index","path":"D:\\Application\\entry\\build\\default\\intermediates\\loader_out\\default\\js\\MainAbility\\pages\\index","type":"directory","isSymbolicLink":false,"children":[{"hashValue":"fd44f1826eb81cb9603d79dcd9bc9e7c","name":"index.abc","path":"D:\\Application\\entry\\build\\default\\intermediates\\loader_out\\default\\js\\MainAbility\\pages\\index\\index.abc","type":"file","isSymbolicLink":false,"fileMetaData":{"size":23132,"lastModifiedTime":1688461729421}},{"hashValue":"50c3fa64f96c792cceb2f1c4267affc6","name":"index.js","path":"D:\\Application\\entry\\build\\default\\intermediates\\loader_out\\default\\js\\MainAbility\\pages\\index\\index.js","type":"file","isSymbolicLink":false,"fileMetaData":{"size":10778,"lastModifiedTime":1688461729348}},{"hashValue":"7cd91bb882b31070fbc2dad606fe8c98","name":"index.js.map","path":"D:\\Application\\entry\\build\\default\\intermediates\\loader_out\\default\\js\\MainAbility\\pages\\index\\index.js.map","type":"file","isSymbolicLink":false,"fileMetaData":{"size":1513,"lastModifiedTime":1688461729348}}]}]},{"hashValue":"278756d9d88122d69fe0fc45f955305b","name":"vendors.abc","path":"D:\\Application\\entry\\build\\default\\intermediates\\loader_out\\default\\js\\MainAbility\\vendors.abc","type":"file","isSymbolicLink":false,"fileMetaData":{"size":5988,"lastModifiedTime":1688461729421}},{"hashValue":"647ad2fab7d5f8a1c317bf490c84884e","name":"vendors.js","path":"D:\\Application\\entry\\build\\default\\intermediates\\loader_out\\default\\js\\MainAbility\\vendors.js","type":"file","isSymbolicLink":false,"fileMetaData":{"size":2218,"lastModifiedTime":1688461729348}},{"hashValue":"a479735dca57ccebb6508c200f981517","name":"vendors.js.map","path":"D:\\Application\\entry\\build\\default\\intermediates\\loader_out\\default\\js\\MainAbility\\vendors.js.map","type":"file","isSymbolicLink":false,"fileMetaData":{"size":493,"lastModifiedTime":1688461729348}}]}]},"D:\\Application\\entry\\build\\default\\intermediates\\loader_out\\default":{"hashValue":"f7189ab6db45e508651f61596c869067","name":"default","path":"D:\\Application\\entry\\build\\default\\intermediates\\loader_out\\default","type":"directory","isSymbolicLink":false,"children":[{"hashValue":"fbd811ecd0d64ec6352365f767b0eb39","name":"js","path":"D:\\Application\\entry\\build\\default\\intermediates\\loader_out\\default\\js","type":"directory","isSymbolicLink":false,"children":[{"hashValue":"764ac8c318367313e9015a8c4c3db646","name":"MainAbility","path":"D:\\Application\\entry\\build\\default\\intermediates\\loader_out\\default\\js\\MainAbility","type":"directory","isSymbolicLink":false,"children":[{"hashValue":"210ad45d91b279078f40c27953edea11","name":"app.abc","path":"D:\\Application\\entry\\build\\default\\intermediates\\loader_out\\default\\js\\MainAbility\\app.abc","type":"file","isSymbolicLink":false,"fileMetaData":{"size":28732,"lastModifiedTime":1688461729423}},{"hashValue":"c8f40671af0594f5e5c7e07c7b449ef5","name":"app.js","path":"D:\\Application\\entry\\build\\default\\intermediates\\loader_out\\default\\js\\MainAbility\\app.js","type":"file","isSymbolicLink":false,"fileMetaData":{"size":13542,"lastModifiedTime":1688461729382}},{"hashValue":"ea3bad378ec1bb65fc0a232a928b9f7e","name":"app.js.map","path":"D:\\Application\\entry\\build\\default\\intermediates\\loader_out\\default\\js\\MainAbility\\app.js.map","type":"file","isSymbolicLink":false,"fileMetaData":{"size":1871,"lastModifiedTime":1688461729348}},{"hashValue":"c5b83b17be069c7889c1adefc8dbd8c7","name":"i18n","path":"D:\\Application\\entry\\build\\default\\intermediates\\loader_out\\default\\js\\MainAbility\\i18n","type":"directory","isSymbolicLink":false,"children":[{"hashValue":"e43635dd195fb1345adcd9d64e64e23a","name":"en-US.json","path":"D:\\Application\\entry\\build\\default\\intermediates\\loader_out\\default\\js\\MainAbility\\i18n\\en-US.json","type":"file","isSymbolicLink":false,"fileMetaData":{"size":83,"lastModifiedTime":1688461729348}},{"hashValue":"96dbe78810cdcafad74a262dc861b1fb","name":"zh-CN.json","path":"D:\\Application\\entry\\build\\default\\intermediates\\loader_out\\default\\js\\MainAbility\\i18n\\zh-CN.json","type":"file","isSymbolicLink":false,"fileMetaData":{"size":85,"lastModifiedTime":1688461729348}}]},{"hashValue":"539680930be7c502d85bbdeffe90fbd0","name":"manifest.json","path":"D:\\Application\\entry\\build\\default\\intermediates\\loader_out\\default\\js\\MainAbility\\manifest.json","type":"file","isSymbolicLink":false,"fileMetaData":{"size":256,"lastModifiedTime":1688461729388}},{"hashValue":"d2aa3bb95501998d008caa784a446372","name":"pages","path":"D:\\Application\\entry\\build\\default\\intermediates\\loader_out\\default\\js\\MainAbility\\pages","type":"directory","isSymbolicLink":false,"children":[{"hashValue":"f4f832c02b43bd5b45e29696aa0fe74d","name":"index","path":"D:\\Application\\entry\\build\\default\\intermediates\\loader_out\\default\\js\\MainAbility\\pages\\index","type":"directory","isSymbolicLink":false,"children":[{"hashValue":"fd44f1826eb81cb9603d79dcd9bc9e7c","name":"index.abc","path":"D:\\Application\\entry\\build\\default\\intermediates\\loader_out\\default\\js\\MainAbility\\pages\\index\\index.abc","type":"file","isSymbolicLink":false,"fileMetaData":{"size":23132,"lastModifiedTime":1688461729421}},{"hashValue":"50c3fa64f96c792cceb2f1c4267affc6","name":"index.js","path":"D:\\Application\\entry\\build\\default\\intermediates\\loader_out\\default\\js\\MainAbility\\pages\\index\\index.js","type":"file","isSymbolicLink":false,"fileMetaData":{"size":10778,"lastModifiedTime":1688461729348}},{"hashValue":"7cd91bb882b31070fbc2dad606fe8c98","name":"index.js.map","path":"D:\\Application\\entry\\build\\default\\intermediates\\loader_out\\default\\js\\MainAbility\\pages\\index\\index.js.map","type":"file","isSymbolicLink":false,"fileMetaData":{"size":1513,"lastModifiedTime":1688461729348}}]}]},{"hashValue":"278756d9d88122d69fe0fc45f955305b","name":"vendors.abc","path":"D:\\Application\\entry\\build\\default\\intermediates\\loader_out\\default\\js\\MainAbility\\vendors.abc","type":"file","isSymbolicLink":false,"fileMetaData":{"size":5988,"lastModifiedTime":1688461729421}},{"hashValue":"647ad2fab7d5f8a1c317bf490c84884e","name":"vendors.js","path":"D:\\Application\\entry\\build\\default\\intermediates\\loader_out\\default\\js\\MainAbility\\vendors.js","type":"file","isSymbolicLink":false,"fileMetaData":{"size":2218,"lastModifiedTime":1688461729348}},{"hashValue":"a479735dca57ccebb6508c200f981517","name":"vendors.js.map","path":"D:\\Application\\entry\\build\\default\\intermediates\\loader_out\\default\\js\\MainAbility\\vendors.js.map","type":"file","isSymbolicLink":false,"fileMetaData":{"size":493,"lastModifiedTime":1688461729348}}]}]}]},"D:\\Application\\entry\\build\\default\\intermediates\\assets_jsbundle\\default\\js":{"hashValue":"fbd811ecd0d64ec6352365f767b0eb39","name":"js","path":"D:\\Application\\entry\\build\\default\\intermediates\\assets_jsbundle\\default\\js","type":"directory","isSymbolicLink":false,"children":[{"hashValue":"764ac8c318367313e9015a8c4c3db646","name":"MainAbility","path":"D:\\Application\\entry\\build\\default\\intermediates\\assets_jsbundle\\default\\js\\MainAbility","type":"directory","isSymbolicLink":false,"children":[{"hashValue":"210ad45d91b279078f40c27953edea11","name":"app.abc","path":"D:\\Application\\entry\\build\\default\\intermediates\\assets_jsbundle\\default\\js\\MainAbility\\app.abc","type":"file","isSymbolicLink":false,"fileMetaData":{"size":28732,"lastModifiedTime":1688461729423}},{"hashValue":"c8f40671af0594f5e5c7e07c7b449ef5","name":"app.js","path":"D:\\Application\\entry\\build\\default\\intermediates\\assets_jsbundle\\default\\js\\MainAbility\\app.js","type":"file","isSymbolicLink":false,"fileMetaData":{"size":13542,"lastModifiedTime":1688461729382}},{"hashValue":"ea3bad378ec1bb65fc0a232a928b9f7e","name":"app.js.map","path":"D:\\Application\\entry\\build\\default\\intermediates\\assets_jsbundle\\default\\js\\MainAbility\\app.js.map","type":"file","isSymbolicLink":false,"fileMetaData":{"size":1871,"lastModifiedTime":1688461729348}},{"hashValue":"c5b83b17be069c7889c1adefc8dbd8c7","name":"i18n","path":"D:\\Application\\entry\\build\\default\\intermediates\\assets_jsbundle\\default\\js\\MainAbility\\i18n","type":"directory","isSymbolicLink":false,"children":[{"hashValue":"e43635dd195fb1345adcd9d64e64e23a","name":"en-US.json","path":"D:\\Application\\entry\\build\\default\\intermediates\\assets_jsbundle\\default\\js\\MainAbility\\i18n\\en-US.json","type":"file","isSymbolicLink":false,"fileMetaData":{"size":83,"lastModifiedTime":1688461729348}},{"hashValue":"96dbe78810cdcafad74a262dc861b1fb","name":"zh-CN.json","path":"D:\\Application\\entry\\build\\default\\intermediates\\assets_jsbundle\\default\\js\\MainAbility\\i18n\\zh-CN.json","type":"file","isSymbolicLink":false,"fileMetaData":{"size":85,"lastModifiedTime":1688461729348}}]},{"hashValue":"539680930be7c502d85bbdeffe90fbd0","name":"manifest.json","path":"D:\\Application\\entry\\build\\default\\intermediates\\assets_jsbundle\\default\\js\\MainAbility\\manifest.json","type":"file","isSymbolicLink":false,"fileMetaData":{"size":256,"lastModifiedTime":1688461729388}},{"hashValue":"d2aa3bb95501998d008caa784a446372","name":"pages","path":"D:\\Application\\entry\\build\\default\\intermediates\\assets_jsbundle\\default\\js\\MainAbility\\pages","type":"directory","isSymbolicLink":false,"children":[{"hashValue":"f4f832c02b43bd5b45e29696aa0fe74d","name":"index","path":"D:\\Application\\entry\\build\\default\\intermediates\\assets_jsbundle\\default\\js\\MainAbility\\pages\\index","type":"directory","isSymbolicLink":false,"children":[{"hashValue":"fd44f1826eb81cb9603d79dcd9bc9e7c","name":"index.abc","path":"D:\\Application\\entry\\build\\default\\intermediates\\assets_jsbundle\\default\\js\\MainAbility\\pages\\index\\index.abc","type":"file","isSymbolicLink":false,"fileMetaData":{"size":23132,"lastModifiedTime":1688461729421}},{"hashValue":"50c3fa64f96c792cceb2f1c4267affc6","name":"index.js","path":"D:\\Application\\entry\\build\\default\\intermediates\\assets_jsbundle\\default\\js\\MainAbility\\pages\\index\\index.js","type":"file","isSymbolicLink":false,"fileMetaData":{"size":10778,"lastModifiedTime":1688461729348}},{"hashValue":"7cd91bb882b31070fbc2dad606fe8c98","name":"index.js.map","path":"D:\\Application\\entry\\build\\default\\intermediates\\assets_jsbundle\\default\\js\\MainAbility\\pages\\index\\index.js.map","type":"file","isSymbolicLink":false,"fileMetaData":{"size":1513,"lastModifiedTime":1688461729348}}]}]},{"hashValue":"278756d9d88122d69fe0fc45f955305b","name":"vendors.abc","path":"D:\\Application\\entry\\build\\default\\intermediates\\assets_jsbundle\\default\\js\\MainAbility\\vendors.abc","type":"file","isSymbolicLink":false,"fileMetaData":{"size":5988,"lastModifiedTime":1688461729421}},{"hashValue":"647ad2fab7d5f8a1c317bf490c84884e","name":"vendors.js","path":"D:\\Application\\entry\\build\\default\\intermediates\\assets_jsbundle\\default\\js\\MainAbility\\vendors.js","type":"file","isSymbolicLink":false,"fileMetaData":{"size":2218,"lastModifiedTime":1688461729348}},{"hashValue":"a479735dca57ccebb6508c200f981517","name":"vendors.js.map","path":"D:\\Application\\entry\\build\\default\\intermediates\\assets_jsbundle\\default\\js\\MainAbility\\vendors.js.map","type":"file","isSymbolicLink":false,"fileMetaData":{"size":493,"lastModifiedTime":1688461729348}}]}]},"D:\\Application\\entry\\build\\default\\intermediates\\assets_jsbundle\\default":{"hashValue":"f7189ab6db45e508651f61596c869067","name":"default","path":"D:\\Application\\entry\\build\\default\\intermediates\\assets_jsbundle\\default","type":"directory","isSymbolicLink":false,"children":[{"hashValue":"fbd811ecd0d64ec6352365f767b0eb39","name":"js","path":"D:\\Application\\entry\\build\\default\\intermediates\\assets_jsbundle\\default\\js","type":"directory","isSymbolicLink":false,"children":[{"hashValue":"764ac8c318367313e9015a8c4c3db646","name":"MainAbility","path":"D:\\Application\\entry\\build\\default\\intermediates\\assets_jsbundle\\default\\js\\MainAbility","type":"directory","isSymbolicLink":false,"children":[{"hashValue":"210ad45d91b279078f40c27953edea11","name":"app.abc","path":"D:\\Application\\entry\\build\\default\\intermediates\\assets_jsbundle\\default\\js\\MainAbility\\app.abc","type":"file","isSymbolicLink":false,"fileMetaData":{"size":28732,"lastModifiedTime":1688461729423}},{"hashValue":"c8f40671af0594f5e5c7e07c7b449ef5","name":"app.js","path":"D:\\Application\\entry\\build\\default\\intermediates\\assets_jsbundle\\default\\js\\MainAbility\\app.js","type":"file","isSymbolicLink":false,"fileMetaData":{"size":13542,"lastModifiedTime":1688461729382}},{"hashValue":"ea3bad378ec1bb65fc0a232a928b9f7e","name":"app.js.map","path":"D:\\Application\\entry\\build\\default\\intermediates\\assets_jsbundle\\default\\js\\MainAbility\\app.js.map","type":"file","isSymbolicLink":false,"fileMetaData":{"size":1871,"lastModifiedTime":1688461729348}},{"hashValue":"c5b83b17be069c7889c1adefc8dbd8c7","name":"i18n","path":"D:\\Application\\entry\\build\\default\\intermediates\\assets_jsbundle\\default\\js\\MainAbility\\i18n","type":"directory","isSymbolicLink":false,"children":[{"hashValue":"e43635dd195fb1345adcd9d64e64e23a","name":"en-US.json","path":"D:\\Application\\entry\\build\\default\\intermediates\\assets_jsbundle\\default\\js\\MainAbility\\i18n\\en-US.json","type":"file","isSymbolicLink":false,"fileMetaData":{"size":83,"lastModifiedTime":1688461729348}},{"hashValue":"96dbe78810cdcafad74a262dc861b1fb","name":"zh-CN.json","path":"D:\\Application\\entry\\build\\default\\intermediates\\assets_jsbundle\\default\\js\\MainAbility\\i18n\\zh-CN.json","type":"file","isSymbolicLink":false,"fileMetaData":{"size":85,"lastModifiedTime":1688461729348}}]},{"hashValue":"539680930be7c502d85bbdeffe90fbd0","name":"manifest.json","path":"D:\\Application\\entry\\build\\default\\intermediates\\assets_jsbundle\\default\\js\\MainAbility\\manifest.json","type":"file","isSymbolicLink":false,"fileMetaData":{"size":256,"lastModifiedTime":1688461729388}},{"hashValue":"d2aa3bb95501998d008caa784a446372","name":"pages","path":"D:\\Application\\entry\\build\\default\\intermediates\\assets_jsbundle\\default\\js\\MainAbility\\pages","type":"directory","isSymbolicLink":false,"children":[{"hashValue":"f4f832c02b43bd5b45e29696aa0fe74d","name":"index","path":"D:\\Application\\entry\\build\\default\\intermediates\\assets_jsbundle\\default\\js\\MainAbility\\pages\\index","type":"directory","isSymbolicLink":false,"children":[{"hashValue":"fd44f1826eb81cb9603d79dcd9bc9e7c","name":"index.abc","path":"D:\\Application\\entry\\build\\default\\intermediates\\assets_jsbundle\\default\\js\\MainAbility\\pages\\index\\index.abc","type":"file","isSymbolicLink":false,"fileMetaData":{"size":23132,"lastModifiedTime":1688461729421}},{"hashValue":"50c3fa64f96c792cceb2f1c4267affc6","name":"index.js","path":"D:\\Application\\entry\\build\\default\\intermediates\\assets_jsbundle\\default\\js\\MainAbility\\pages\\index\\index.js","type":"file","isSymbolicLink":false,"fileMetaData":{"size":10778,"lastModifiedTime":1688461729348}},{"hashValue":"7cd91bb882b31070fbc2dad606fe8c98","name":"index.js.map","path":"D:\\Application\\entry\\build\\default\\intermediates\\assets_jsbundle\\default\\js\\MainAbility\\pages\\index\\index.js.map","type":"file","isSymbolicLink":false,"fileMetaData":{"size":1513,"lastModifiedTime":1688461729348}}]}]},{"hashValue":"278756d9d88122d69fe0fc45f955305b","name":"vendors.abc","path":"D:\\Application\\entry\\build\\default\\intermediates\\assets_jsbundle\\default\\js\\MainAbility\\vendors.abc","type":"file","isSymbolicLink":false,"fileMetaData":{"size":5988,"lastModifiedTime":1688461729421}},{"hashValue":"647ad2fab7d5f8a1c317bf490c84884e","name":"vendors.js","path":"D:\\Application\\entry\\build\\default\\intermediates\\assets_jsbundle\\default\\js\\MainAbility\\vendors.js","type":"file","isSymbolicLink":false,"fileMetaData":{"size":2218,"lastModifiedTime":1688461729348}},{"hashValue":"a479735dca57ccebb6508c200f981517","name":"vendors.js.map","path":"D:\\Application\\entry\\build\\default\\intermediates\\assets_jsbundle\\default\\js\\MainAbility\\vendors.js.map","type":"file","isSymbolicLink":false,"fileMetaData":{"size":493,"lastModifiedTime":1688461729348}}]}]}]},"D:\\Application\\entry\\build\\default\\intermediates\\res\\default\\config.json":{"hashValue":"7ab94cad0ca9d20eacef971b8c844fad","name":"config.json","path":"D:\\Application\\entry\\build\\default\\intermediates\\res\\default\\config.json","type":"file","isSymbolicLink":false,"fileMetaData":{"size":2352,"lastModifiedTime":1688461727095}},"D:\\Application\\entry\\build\\default\\intermediates\\res\\default\\resources":{"hashValue":"c384355f69733ff77f925512574987bd","name":"resources","path":"D:\\Application\\entry\\build\\default\\intermediates\\res\\default\\resources","type":"directory","isSymbolicLink":false,"children":[{"hashValue":"a5375fa2da5841fa53b639da938ade77","name":"base","path":"D:\\Application\\entry\\build\\default\\intermediates\\res\\default\\resources\\base","type":"directory","isSymbolicLink":false,"children":[{"hashValue":"5be04b5645efd573c74f54ada5a9fac8","name":"media","path":"D:\\Application\\entry\\build\\default\\intermediates\\res\\default\\resources\\base\\media","type":"directory","isSymbolicLink":false,"children":[{"hashValue":"a51f723ed916a0b72c691fc7594bbd1e","name":"icon.png","path":"D:\\Application\\entry\\build\\default\\intermediates\\res\\default\\resources\\base\\media\\icon.png","type":"file","isSymbolicLink":false,"fileMetaData":{"size":6790,"lastModifiedTime":1688438694167}}]}]},{"hashValue":"","name":"rawfile","path":"D:\\Application\\entry\\build\\default\\intermediates\\res\\default\\resources\\rawfile","type":"directory","isSymbolicLink":false,"children":[]}]},"D:\\Application\\entry\\build\\default\\intermediates\\res\\default\\resources.index":{"hashValue":"dede9f3982ecc1e0f1d89fb3c7574651","name":"resources.index","path":"D:\\Application\\entry\\build\\default\\intermediates\\res\\default\\resources.index","type":"file","isSymbolicLink":false,"fileMetaData":{"size":811,"lastModifiedTime":1688461727095}},"D:\\Application\\entry\\build\\default\\outputs\\default\\entry-default-unsigned.hap":{"hashValue":"3fcf420f3a9940427591dd5bb6701575","name":"entry-default-unsigned.hap","path":"D:\\Application\\entry\\build\\default\\outputs\\default\\entry-default-unsigned.hap","type":"file","isSymbolicLink":false,"fileMetaData":{"size":100559,"lastModifiedTime":1688461731537}},"D:\\Application\\entry\\build\\default\\outputs\\default\\entry-default-signed.hap":{"hashValue":"4ac089c839bef0bb81fb4aa753fbc58f","name":"entry-default-signed.hap","path":"D:\\Application\\entry\\build\\default\\outputs\\default\\entry-default-signed.hap","type":"file","isSymbolicLink":false,"fileMetaData":{"size":105339,"lastModifiedTime":1688461733936}},"C:\\Users\\sunmingze\\.ohos\\config\\openharmony\\auto_ohos_default_Application_com.example.accessibleabilitylist.cer":{"hashValue":"b663d7943a2c831ab05303b5b9d5aa6f","name":"auto_ohos_default_Application_com.example.accessibleabilitylist.cer","path":"C:\\Users\\sunmingze\\.ohos\\config\\openharmony\\auto_ohos_default_Application_com.example.accessibleabilitylist.cer","type":"file","isSymbolicLink":false,"fileMetaData":{"size":1698,"lastModifiedTime":1688461644541}},"C:\\Users\\sunmingze\\.ohos\\config\\openharmony\\auto_ohos_default_Application_com.example.accessibleabilitylist.p7b":{"hashValue":"14d270e1d6ca19d2b0928deaf246609d","name":"auto_ohos_default_Application_com.example.accessibleabilitylist.p7b","path":"C:\\Users\\sunmingze\\.ohos\\config\\openharmony\\auto_ohos_default_Application_com.example.accessibleabilitylist.p7b","type":"file","isSymbolicLink":false,"fileMetaData":{"size":3434,"lastModifiedTime":1688461646008}},"C:\\Users\\sunmingze\\.ohos\\config\\openharmony\\auto_ohos_default_Application_com.example.accessibleabilitylist.p12":{"hashValue":"9a9f40b2c65449d81eafabdad1c125c7","name":"auto_ohos_default_Application_com.example.accessibleabilitylist.p12","path":"C:\\Users\\sunmingze\\.ohos\\config\\openharmony\\auto_ohos_default_Application_com.example.accessibleabilitylist.p12","type":"file","isSymbolicLink":false,"fileMetaData":{"size":1128,"lastModifiedTime":1688461643221}},"D:\\Application\\entry\\src\\ohosTest\\config.json":{"hashValue":"57ad69494916ff3387a7056433fa7226","name":"config.json","path":"D:\\Application\\entry\\src\\ohosTest\\config.json","type":"file","isSymbolicLink":false,"fileMetaData":{"size":1855,"lastModifiedTime":1688461234443}},"D:\\Application\\entry\\build\\default\\intermediates\\hap_metadata\\ohosTest\\output_metadata.json":{"hashValue":"5d82b52eac369da9fbe21b3d405add86","name":"output_metadata.json","path":"D:\\Application\\entry\\build\\default\\intermediates\\hap_metadata\\ohosTest\\output_metadata.json","type":"file","isSymbolicLink":false,"fileMetaData":{"size":93,"lastModifiedTime":1688461734645}},"D:\\Application\\entry\\build\\default\\intermediates\\merge_profile\\ohosTest\\config.json":{"hashValue":"c281a8207221a5e7626530edc64f8462","name":"config.json","path":"D:\\Application\\entry\\build\\default\\intermediates\\merge_profile\\ohosTest\\config.json","type":"file","isSymbolicLink":false,"fileMetaData":{"size":1646,"lastModifiedTime":1688461734650}},"D:\\Application\\entry\\build\\default\\intermediates\\manifest\\ohosTest":{"hashValue":"4bb87160d0fa23d11e48a1d4fe607605","name":"ohosTest","path":"D:\\Application\\entry\\build\\default\\intermediates\\manifest\\ohosTest","type":"directory","isSymbolicLink":false,"children":[{"hashValue":"10338a99ba1df4faf08024532efafc70","name":"TestAbility","path":"D:\\Application\\entry\\build\\default\\intermediates\\manifest\\ohosTest\\TestAbility","type":"directory","isSymbolicLink":false,"children":[{"hashValue":"892a14039f18f7563cc5c79896a9b6d9","name":"manifest.json","path":"D:\\Application\\entry\\build\\default\\intermediates\\manifest\\ohosTest\\TestAbility\\manifest.json","type":"file","isSymbolicLink":false,"fileMetaData":{"size":256,"lastModifiedTime":1688461734701}}]}]},"D:\\Application\\entry\\build\\default\\outputs\\ohosTest\\pack.info":{"hashValue":"7f342fd303db1987eb6b947046200df3","name":"pack.info","path":"D:\\Application\\entry\\build\\default\\outputs\\ohosTest\\pack.info","type":"file","isSymbolicLink":false,"fileMetaData":{"size":903,"lastModifiedTime":1688461734703}},"D:\\Application\\entry\\build\\default\\intermediates\\process_profile\\ohosTest\\config.json":{"hashValue":"f2493e6d66a712f681b643a0f27b26ff","name":"config.json","path":"D:\\Application\\entry\\build\\default\\intermediates\\process_profile\\ohosTest\\config.json","type":"file","isSymbolicLink":false,"fileMetaData":{"size":1257,"lastModifiedTime":1688461734883}},"D:\\Application\\entry\\build\\default\\intermediates\\loader\\ohosTest\\TestAbility\\loader.json":{"hashValue":"ac2aa29f6ba1698bf3c08518a1088319","name":"loader.json","path":"D:\\Application\\entry\\build\\default\\intermediates\\loader\\ohosTest\\TestAbility\\loader.json","type":"file","isSymbolicLink":false,"fileMetaData":{"size":142,"lastModifiedTime":1688461734886}},"D:\\Application\\entry\\build\\default\\intermediates\\res\\ohosTest\\resConfig.json":{"hashValue":"d3e5da10cc88b55a498e8787140be638","name":"resConfig.json","path":"D:\\Application\\entry\\build\\default\\intermediates\\res\\ohosTest\\resConfig.json","type":"file","isSymbolicLink":false,"fileMetaData":{"size":459,"lastModifiedTime":1688461734890}},"D:\\Application\\entry\\build\\default\\intermediates\\libs\\ohosTest":{"hashValue":"","name":"ohosTest","path":"D:\\Application\\entry\\build\\default\\intermediates\\libs\\ohosTest","type":"directory","isSymbolicLink":false,"children":[]},"D:\\Application\\entry\\src\\ohosTest\\resources":{"hashValue":"52e2d5e72016bcfeb7c84cc9f04a0eef","name":"resources","path":"D:\\Application\\entry\\src\\ohosTest\\resources","type":"directory","isSymbolicLink":false,"children":[{"hashValue":"78c733652a9395d5fc1f927faafd9b62","name":"base","path":"D:\\Application\\entry\\src\\ohosTest\\resources\\base","type":"directory","isSymbolicLink":false,"children":[{"hashValue":"efe17839128e24247d100043733f71ab","name":"element","path":"D:\\Application\\entry\\src\\ohosTest\\resources\\base\\element","type":"directory","isSymbolicLink":false,"children":[{"hashValue":"200843f70ee979c61e63586717cd92b9","name":"string.json","path":"D:\\Application\\entry\\src\\ohosTest\\resources\\base\\element\\string.json","type":"file","isSymbolicLink":false,"fileMetaData":{"size":177,"lastModifiedTime":1688438694087}}]},{"hashValue":"15ad28015a4943708fccc514d361fcbc","name":"media","path":"D:\\Application\\entry\\src\\ohosTest\\resources\\base\\media","type":"directory","isSymbolicLink":false,"children":[{"hashValue":"a75f510daf2a968450be3733ebfd450c","name":"icon.png","path":"D:\\Application\\entry\\src\\ohosTest\\resources\\base\\media\\icon.png","type":"file","isSymbolicLink":false,"fileMetaData":{"size":6790,"lastModifiedTime":1688438694095}}]},{"hashValue":"7654f74531ded4f7df5ebdb776c437a1","name":"profile","path":"D:\\Application\\entry\\src\\ohosTest\\resources\\base\\profile","type":"directory","isSymbolicLink":false,"children":[{"hashValue":"2e5732a0b96269dce11fc2419ce5e783","name":"test_pages.json","path":"D:\\Application\\entry\\src\\ohosTest\\resources\\base\\profile\\test_pages.json","type":"file","isSymbolicLink":false,"fileMetaData":{"size":49,"lastModifiedTime":1688438694102}}]}]}]},"D:\\Application\\entry\\build\\default\\intermediates\\res\\ohosTest":{"hashValue":"cd23e8e07d91e1cc3b67b919f00a0b9e","name":"ohosTest","path":"D:\\Application\\entry\\build\\default\\intermediates\\res\\ohosTest","type":"directory","isSymbolicLink":false,"children":[{"hashValue":"3c20b9a05a10977ee66ff48b576e412c","name":"config.json","path":"D:\\Application\\entry\\build\\default\\intermediates\\res\\ohosTest\\config.json","type":"file","isSymbolicLink":false,"fileMetaData":{"size":2900,"lastModifiedTime":1688461735001}},{"hashValue":"d3e5da10cc88b55a498e8787140be638","name":"resConfig.json","path":"D:\\Application\\entry\\build\\default\\intermediates\\res\\ohosTest\\resConfig.json","type":"file","isSymbolicLink":false,"fileMetaData":{"size":459,"lastModifiedTime":1688461734890}},{"hashValue":"f21d9664024ebbb34940df857a636a01","name":"resources","path":"D:\\Application\\entry\\build\\default\\intermediates\\res\\ohosTest\\resources","type":"directory","isSymbolicLink":false,"children":[{"hashValue":"6bf07c2c8afe5e472d7486bf4c901722","name":"base","path":"D:\\Application\\entry\\build\\default\\intermediates\\res\\ohosTest\\resources\\base","type":"directory","isSymbolicLink":false,"children":[{"hashValue":"15ad28015a4943708fccc514d361fcbc","name":"media","path":"D:\\Application\\entry\\build\\default\\intermediates\\res\\ohosTest\\resources\\base\\media","type":"directory","isSymbolicLink":false,"children":[{"hashValue":"a75f510daf2a968450be3733ebfd450c","name":"icon.png","path":"D:\\Application\\entry\\build\\default\\intermediates\\res\\ohosTest\\resources\\base\\media\\icon.png","type":"file","isSymbolicLink":false,"fileMetaData":{"size":6790,"lastModifiedTime":1688438694095}}]},{"hashValue":"7654f74531ded4f7df5ebdb776c437a1","name":"profile","path":"D:\\Application\\entry\\build\\default\\intermediates\\res\\ohosTest\\resources\\base\\profile","type":"directory","isSymbolicLink":false,"children":[{"hashValue":"2e5732a0b96269dce11fc2419ce5e783","name":"test_pages.json","path":"D:\\Application\\entry\\build\\default\\intermediates\\res\\ohosTest\\resources\\base\\profile\\test_pages.json","type":"file","isSymbolicLink":false,"fileMetaData":{"size":49,"lastModifiedTime":1688438694102}}]}]}]},{"hashValue":"b29b7e69dcda743c0abad604c9ab3982","name":"resources.index","path":"D:\\Application\\entry\\build\\default\\intermediates\\res\\ohosTest\\resources.index","type":"file","isSymbolicLink":false,"fileMetaData":{"size":422,"lastModifiedTime":1688461735001}},{"hashValue":"790f45a6573de38b3e4b7bcc1ec9b26b","name":"ResourceTable.txt","path":"D:\\Application\\entry\\build\\default\\intermediates\\res\\ohosTest\\ResourceTable.txt","type":"file","isSymbolicLink":false,"fileMetaData":{"size":122,"lastModifiedTime":1688461735000}}]},"D:\\Application\\entry\\build\\default\\cache\\ohosTest\\r\\ResourceTable.h":{"hashValue":"1ae414439c650c5a48d7386804494fb6","name":"ResourceTable.h","path":"D:\\Application\\entry\\build\\default\\cache\\ohosTest\\r\\ResourceTable.h","type":"file","isSymbolicLink":false,"fileMetaData":{"size":896,"lastModifiedTime":1688461735000}},"D:\\Application\\entry\\build\\default\\cache\\ohosTest\\r":{"hashValue":"1428af9417cfc8308633e4379888eee0","name":"r","path":"D:\\Application\\entry\\build\\default\\cache\\ohosTest\\r","type":"directory","isSymbolicLink":false,"children":[{"hashValue":"1ae414439c650c5a48d7386804494fb6","name":"ResourceTable.h","path":"D:\\Application\\entry\\build\\default\\cache\\ohosTest\\r\\ResourceTable.h","type":"file","isSymbolicLink":false,"fileMetaData":{"size":896,"lastModifiedTime":1688461735000}}]},"D:\\Application\\entry\\build\\default\\intermediates\\loader\\ohosTest":{"hashValue":"423a7eaaee245399dd7ca00c43b4c96b","name":"ohosTest","path":"D:\\Application\\entry\\build\\default\\intermediates\\loader\\ohosTest","type":"directory","isSymbolicLink":false,"children":[{"hashValue":"e905e0c1811e653f428450022c24433c","name":"TestAbility","path":"D:\\Application\\entry\\build\\default\\intermediates\\loader\\ohosTest\\TestAbility","type":"directory","isSymbolicLink":false,"children":[{"hashValue":"ac2aa29f6ba1698bf3c08518a1088319","name":"loader.json","path":"D:\\Application\\entry\\build\\default\\intermediates\\loader\\ohosTest\\TestAbility\\loader.json","type":"file","isSymbolicLink":false,"fileMetaData":{"size":142,"lastModifiedTime":1688461734886}}]}]},"D:\\Application\\entry\\build\\default\\intermediates\\res\\ohosTest\\ResourceTable.txt":{"hashValue":"790f45a6573de38b3e4b7bcc1ec9b26b","name":"ResourceTable.txt","path":"D:\\Application\\entry\\build\\default\\intermediates\\res\\ohosTest\\ResourceTable.txt","type":"file","isSymbolicLink":false,"fileMetaData":{"size":122,"lastModifiedTime":1688461735000}},"D:\\Application\\entry\\build\\default\\intermediates\\loader_out\\ohosTest\\ets":{"hashValue":"","name":"emptyroot","path":"","type":"unknown","isSymbolicLink":false,"children":[]},"D:\\Application\\entry\\src\\ohosTest\\js":{"hashValue":"587519055a923b0ae42e469577f04998","name":"js","path":"D:\\Application\\entry\\src\\ohosTest\\js","type":"directory","isSymbolicLink":false,"children":[{"hashValue":"898045777ab2731ea3912573382ca745","name":"test","path":"D:\\Application\\entry\\src\\ohosTest\\js\\test","type":"directory","isSymbolicLink":false,"children":[{"hashValue":"b20e7a9441f68dc02678d0aaebf6be72","name":"AccessibleAbilityList.test.js","path":"D:\\Application\\entry\\src\\ohosTest\\js\\test\\AccessibleAbilityList.test.js","type":"file","isSymbolicLink":false,"fileMetaData":{"size":23749,"lastModifiedTime":1688461410085}},{"hashValue":"203f897948dbed059a2249508d76e045","name":"List.test.js","path":"D:\\Application\\entry\\src\\ohosTest\\js\\test\\List.test.js","type":"file","isSymbolicLink":false,"fileMetaData":{"size":743,"lastModifiedTime":1688461422386}}]},{"hashValue":"3329e97a5ff692d7065884c7364090ec","name":"TestAbility","path":"D:\\Application\\entry\\src\\ohosTest\\js\\TestAbility","type":"directory","isSymbolicLink":false,"children":[{"hashValue":"07abe86dee570c84f50ab83c121d9ecf","name":"app.js","path":"D:\\Application\\entry\\src\\ohosTest\\js\\TestAbility\\app.js","type":"file","isSymbolicLink":false,"fileMetaData":{"size":1356,"lastModifiedTime":1688461433818}},{"hashValue":"d2691eba85c03449bc8a0a7b2d39b2d9","name":"i18n","path":"D:\\Application\\entry\\src\\ohosTest\\js\\TestAbility\\i18n","type":"directory","isSymbolicLink":false,"children":[{"hashValue":"48bc596a949a553dcf82ce3f682bff71","name":"en-US.json","path":"D:\\Application\\entry\\src\\ohosTest\\js\\TestAbility\\i18n\\en-US.json","type":"file","isSymbolicLink":false,"fileMetaData":{"size":83,"lastModifiedTime":1688438694051}},{"hashValue":"94a467bd9a0de883352e3579fc51bb75","name":"zh-CN.json","path":"D:\\Application\\entry\\src\\ohosTest\\js\\TestAbility\\i18n\\zh-CN.json","type":"file","isSymbolicLink":false,"fileMetaData":{"size":85,"lastModifiedTime":1688438694057}}]},{"hashValue":"8db2e089441124d1213c2b81d5961e70","name":"pages","path":"D:\\Application\\entry\\src\\ohosTest\\js\\TestAbility\\pages","type":"directory","isSymbolicLink":false,"children":[{"hashValue":"77a0f71344c3dbdf6f65962b3180d81e","name":"index","path":"D:\\Application\\entry\\src\\ohosTest\\js\\TestAbility\\pages\\index","type":"directory","isSymbolicLink":false,"children":[{"hashValue":"a701eaff119ceded011adf6e8f830973","name":"index.css","path":"D:\\Application\\entry\\src\\ohosTest\\js\\TestAbility\\pages\\index\\index.css","type":"file","isSymbolicLink":false,"fileMetaData":{"size":499,"lastModifiedTime":1688438694066}},{"hashValue":"7c1df440f81b81d42e8477fa0e9ba847","name":"index.hml","path":"D:\\Application\\entry\\src\\ohosTest\\js\\TestAbility\\pages\\index\\index.hml","type":"file","isSymbolicLink":false,"fileMetaData":{"size":114,"lastModifiedTime":1688438694071}},{"hashValue":"88f195a82a3eb6c1d1bd3e384e3f95e6","name":"index.js","path":"D:\\Application\\entry\\src\\ohosTest\\js\\TestAbility\\pages\\index\\index.js","type":"file","isSymbolicLink":false,"fileMetaData":{"size":735,"lastModifiedTime":1688461442127}}]}]}]},{"hashValue":"c77aef4399e29679b0c09f4d886874f3","name":"TestRunner","path":"D:\\Application\\entry\\src\\ohosTest\\js\\TestRunner","type":"directory","isSymbolicLink":false,"children":[{"hashValue":"c1001993f9309f3e93bfbf503d2e7c8d","name":"OpenHarmonyTestRunner.js","path":"D:\\Application\\entry\\src\\ohosTest\\js\\TestRunner\\OpenHarmonyTestRunner.js","type":"file","isSymbolicLink":false,"fileMetaData":{"size":1925,"lastModifiedTime":1688461449408}}]}]},"D:\\Application\\entry\\build\\default\\intermediates\\loader_out\\ohosTest\\js":{"hashValue":"6640c7142c1e67060b5a24eaba887d4a","name":"js","path":"D:\\Application\\entry\\build\\default\\intermediates\\loader_out\\ohosTest\\js","type":"directory","isSymbolicLink":false,"children":[{"hashValue":"04dd2f3ba5335b94ab06d489083a7a24","name":"TestAbility","path":"D:\\Application\\entry\\build\\default\\intermediates\\loader_out\\ohosTest\\js\\TestAbility","type":"directory","isSymbolicLink":false,"children":[{"hashValue":"86086ff9ee39ef04922b46eaeb427c8d","name":"app.abc","path":"D:\\Application\\entry\\build\\default\\intermediates\\loader_out\\ohosTest\\js\\TestAbility\\app.abc","type":"file","isSymbolicLink":false,"fileMetaData":{"size":76816,"lastModifiedTime":1688461738574}},{"hashValue":"329aaea2d2e8ed1f88f0666b9a153109","name":"app.js","path":"D:\\Application\\entry\\build\\default\\intermediates\\loader_out\\ohosTest\\js\\TestAbility\\app.js","type":"file","isSymbolicLink":false,"fileMetaData":{"size":32432,"lastModifiedTime":1688461738461}},{"hashValue":"1fa26a0479cff127e5ce4ad10745fc8a","name":"app.js.map","path":"D:\\Application\\entry\\build\\default\\intermediates\\loader_out\\ohosTest\\js\\TestAbility\\app.js.map","type":"file","isSymbolicLink":false,"fileMetaData":{"size":16823,"lastModifiedTime":1688461738427}},{"hashValue":"03b29350fdf80f9ee80b41db5ed42f93","name":"i18n","path":"D:\\Application\\entry\\build\\default\\intermediates\\loader_out\\ohosTest\\js\\TestAbility\\i18n","type":"directory","isSymbolicLink":false,"children":[{"hashValue":"31b44c2273c6b694151084ace0747385","name":"en-US.json","path":"D:\\Application\\entry\\build\\default\\intermediates\\loader_out\\ohosTest\\js\\TestAbility\\i18n\\en-US.json","type":"file","isSymbolicLink":false,"fileMetaData":{"size":83,"lastModifiedTime":1688461738428}},{"hashValue":"8192745c65142c57ddd31b6b8cb0b7aa","name":"zh-CN.json","path":"D:\\Application\\entry\\build\\default\\intermediates\\loader_out\\ohosTest\\js\\TestAbility\\i18n\\zh-CN.json","type":"file","isSymbolicLink":false,"fileMetaData":{"size":85,"lastModifiedTime":1688461738427}}]},{"hashValue":"532e7badc2f31e6fabd604c3844e97d7","name":"manifest.json","path":"D:\\Application\\entry\\build\\default\\intermediates\\loader_out\\ohosTest\\js\\TestAbility\\manifest.json","type":"file","isSymbolicLink":false,"fileMetaData":{"size":256,"lastModifiedTime":1688461738467}},{"hashValue":"c3cad7ce16216ce3b3e47b0950583642","name":"pages","path":"D:\\Application\\entry\\build\\default\\intermediates\\loader_out\\ohosTest\\js\\TestAbility\\pages","type":"directory","isSymbolicLink":false,"children":[{"hashValue":"6abee471718a361b2b71452f7af76ad0","name":"index","path":"D:\\Application\\entry\\build\\default\\intermediates\\loader_out\\ohosTest\\js\\TestAbility\\pages\\index","type":"directory","isSymbolicLink":false,"children":[{"hashValue":"a08b6a4108ecd2bf9fedaca82ab0a7a9","name":"index.abc","path":"D:\\Application\\entry\\build\\default\\intermediates\\loader_out\\ohosTest\\js\\TestAbility\\pages\\index\\index.abc","type":"file","isSymbolicLink":false,"fileMetaData":{"size":23220,"lastModifiedTime":1688461738569}},{"hashValue":"8fda7d3e71fd5c84ba499854441d6d75","name":"index.js","path":"D:\\Application\\entry\\build\\default\\intermediates\\loader_out\\ohosTest\\js\\TestAbility\\pages\\index\\index.js","type":"file","isSymbolicLink":false,"fileMetaData":{"size":10850,"lastModifiedTime":1688461738427}},{"hashValue":"8c3252a265bb5033fcf06b3db51e54c0","name":"index.js.map","path":"D:\\Application\\entry\\build\\default\\intermediates\\loader_out\\ohosTest\\js\\TestAbility\\pages\\index\\index.js.map","type":"file","isSymbolicLink":false,"fileMetaData":{"size":1529,"lastModifiedTime":1688461738428}}]}]},{"hashValue":"c3002cd052fd59226a8c7908464fb67c","name":"vendors.abc","path":"D:\\Application\\entry\\build\\default\\intermediates\\loader_out\\ohosTest\\js\\TestAbility\\vendors.abc","type":"file","isSymbolicLink":false,"fileMetaData":{"size":441768,"lastModifiedTime":1688461738610}},{"hashValue":"5ea847f7af8e1eccc0aaf4ff7c717cfe","name":"vendors.js","path":"D:\\Application\\entry\\build\\default\\intermediates\\loader_out\\ohosTest\\js\\TestAbility\\vendors.js","type":"file","isSymbolicLink":false,"fileMetaData":{"size":185511,"lastModifiedTime":1688461738427}},{"hashValue":"c1e7143b09b57b67dc2aa9e5f9c85dd4","name":"vendors.js.map","path":"D:\\Application\\entry\\build\\default\\intermediates\\loader_out\\ohosTest\\js\\TestAbility\\vendors.js.map","type":"file","isSymbolicLink":false,"fileMetaData":{"size":125504,"lastModifiedTime":1688461738427}}]},{"hashValue":"fdd2f79b68e8421134492f6a557e9c57","name":"TestRunner","path":"D:\\Application\\entry\\build\\default\\intermediates\\loader_out\\ohosTest\\js\\TestRunner","type":"directory","isSymbolicLink":false,"children":[{"hashValue":"0e512e97f1b7d41dc8b3e962c6b6f339","name":"OpenHarmonyTestRunner.abc","path":"D:\\Application\\entry\\build\\default\\intermediates\\loader_out\\ohosTest\\js\\TestRunner\\OpenHarmonyTestRunner.abc","type":"file","isSymbolicLink":false,"fileMetaData":{"size":22916,"lastModifiedTime":1688461737683}},{"hashValue":"eaff65eb285e9fc32c73ae07a40550ec","name":"OpenHarmonyTestRunner.js","path":"D:\\Application\\entry\\build\\default\\intermediates\\loader_out\\ohosTest\\js\\TestRunner\\OpenHarmonyTestRunner.js","type":"file","isSymbolicLink":false,"fileMetaData":{"size":10141,"lastModifiedTime":1688461737610}},{"hashValue":"df9cf1f7c2bd8662691cd94da6f49298","name":"OpenHarmonyTestRunner.js.map","path":"D:\\Application\\entry\\build\\default\\intermediates\\loader_out\\ohosTest\\js\\TestRunner\\OpenHarmonyTestRunner.js.map","type":"file","isSymbolicLink":false,"fileMetaData":{"size":2680,"lastModifiedTime":1688461737610}}]}]},"D:\\Application\\entry\\build\\default\\intermediates\\loader_out\\ohosTest":{"hashValue":"e8ebb4be018f2cc14a1da15218e55e33","name":"ohosTest","path":"D:\\Application\\entry\\build\\default\\intermediates\\loader_out\\ohosTest","type":"directory","isSymbolicLink":false,"children":[{"hashValue":"6640c7142c1e67060b5a24eaba887d4a","name":"js","path":"D:\\Application\\entry\\build\\default\\intermediates\\loader_out\\ohosTest\\js","type":"directory","isSymbolicLink":false,"children":[{"hashValue":"04dd2f3ba5335b94ab06d489083a7a24","name":"TestAbility","path":"D:\\Application\\entry\\build\\default\\intermediates\\loader_out\\ohosTest\\js\\TestAbility","type":"directory","isSymbolicLink":false,"children":[{"hashValue":"86086ff9ee39ef04922b46eaeb427c8d","name":"app.abc","path":"D:\\Application\\entry\\build\\default\\intermediates\\loader_out\\ohosTest\\js\\TestAbility\\app.abc","type":"file","isSymbolicLink":false,"fileMetaData":{"size":76816,"lastModifiedTime":1688461738574}},{"hashValue":"329aaea2d2e8ed1f88f0666b9a153109","name":"app.js","path":"D:\\Application\\entry\\build\\default\\intermediates\\loader_out\\ohosTest\\js\\TestAbility\\app.js","type":"file","isSymbolicLink":false,"fileMetaData":{"size":32432,"lastModifiedTime":1688461738461}},{"hashValue":"1fa26a0479cff127e5ce4ad10745fc8a","name":"app.js.map","path":"D:\\Application\\entry\\build\\default\\intermediates\\loader_out\\ohosTest\\js\\TestAbility\\app.js.map","type":"file","isSymbolicLink":false,"fileMetaData":{"size":16823,"lastModifiedTime":1688461738427}},{"hashValue":"03b29350fdf80f9ee80b41db5ed42f93","name":"i18n","path":"D:\\Application\\entry\\build\\default\\intermediates\\loader_out\\ohosTest\\js\\TestAbility\\i18n","type":"directory","isSymbolicLink":false,"children":[{"hashValue":"31b44c2273c6b694151084ace0747385","name":"en-US.json","path":"D:\\Application\\entry\\build\\default\\intermediates\\loader_out\\ohosTest\\js\\TestAbility\\i18n\\en-US.json","type":"file","isSymbolicLink":false,"fileMetaData":{"size":83,"lastModifiedTime":1688461738428}},{"hashValue":"8192745c65142c57ddd31b6b8cb0b7aa","name":"zh-CN.json","path":"D:\\Application\\entry\\build\\default\\intermediates\\loader_out\\ohosTest\\js\\TestAbility\\i18n\\zh-CN.json","type":"file","isSymbolicLink":false,"fileMetaData":{"size":85,"lastModifiedTime":1688461738427}}]},{"hashValue":"532e7badc2f31e6fabd604c3844e97d7","name":"manifest.json","path":"D:\\Application\\entry\\build\\default\\intermediates\\loader_out\\ohosTest\\js\\TestAbility\\manifest.json","type":"file","isSymbolicLink":false,"fileMetaData":{"size":256,"lastModifiedTime":1688461738467}},{"hashValue":"c3cad7ce16216ce3b3e47b0950583642","name":"pages","path":"D:\\Application\\entry\\build\\default\\intermediates\\loader_out\\ohosTest\\js\\TestAbility\\pages","type":"directory","isSymbolicLink":false,"children":[{"hashValue":"6abee471718a361b2b71452f7af76ad0","name":"index","path":"D:\\Application\\entry\\build\\default\\intermediates\\loader_out\\ohosTest\\js\\TestAbility\\pages\\index","type":"directory","isSymbolicLink":false,"children":[{"hashValue":"a08b6a4108ecd2bf9fedaca82ab0a7a9","name":"index.abc","path":"D:\\Application\\entry\\build\\default\\intermediates\\loader_out\\ohosTest\\js\\TestAbility\\pages\\index\\index.abc","type":"file","isSymbolicLink":false,"fileMetaData":{"size":23220,"lastModifiedTime":1688461738569}},{"hashValue":"8fda7d3e71fd5c84ba499854441d6d75","name":"index.js","path":"D:\\Application\\entry\\build\\default\\intermediates\\loader_out\\ohosTest\\js\\TestAbility\\pages\\index\\index.js","type":"file","isSymbolicLink":false,"fileMetaData":{"size":10850,"lastModifiedTime":1688461738427}},{"hashValue":"8c3252a265bb5033fcf06b3db51e54c0","name":"index.js.map","path":"D:\\Application\\entry\\build\\default\\intermediates\\loader_out\\ohosTest\\js\\TestAbility\\pages\\index\\index.js.map","type":"file","isSymbolicLink":false,"fileMetaData":{"size":1529,"lastModifiedTime":1688461738428}}]}]},{"hashValue":"c3002cd052fd59226a8c7908464fb67c","name":"vendors.abc","path":"D:\\Application\\entry\\build\\default\\intermediates\\loader_out\\ohosTest\\js\\TestAbility\\vendors.abc","type":"file","isSymbolicLink":false,"fileMetaData":{"size":441768,"lastModifiedTime":1688461738610}},{"hashValue":"5ea847f7af8e1eccc0aaf4ff7c717cfe","name":"vendors.js","path":"D:\\Application\\entry\\build\\default\\intermediates\\loader_out\\ohosTest\\js\\TestAbility\\vendors.js","type":"file","isSymbolicLink":false,"fileMetaData":{"size":185511,"lastModifiedTime":1688461738427}},{"hashValue":"c1e7143b09b57b67dc2aa9e5f9c85dd4","name":"vendors.js.map","path":"D:\\Application\\entry\\build\\default\\intermediates\\loader_out\\ohosTest\\js\\TestAbility\\vendors.js.map","type":"file","isSymbolicLink":false,"fileMetaData":{"size":125504,"lastModifiedTime":1688461738427}}]},{"hashValue":"fdd2f79b68e8421134492f6a557e9c57","name":"TestRunner","path":"D:\\Application\\entry\\build\\default\\intermediates\\loader_out\\ohosTest\\js\\TestRunner","type":"directory","isSymbolicLink":false,"children":[{"hashValue":"0e512e97f1b7d41dc8b3e962c6b6f339","name":"OpenHarmonyTestRunner.abc","path":"D:\\Application\\entry\\build\\default\\intermediates\\loader_out\\ohosTest\\js\\TestRunner\\OpenHarmonyTestRunner.abc","type":"file","isSymbolicLink":false,"fileMetaData":{"size":22916,"lastModifiedTime":1688461737683}},{"hashValue":"eaff65eb285e9fc32c73ae07a40550ec","name":"OpenHarmonyTestRunner.js","path":"D:\\Application\\entry\\build\\default\\intermediates\\loader_out\\ohosTest\\js\\TestRunner\\OpenHarmonyTestRunner.js","type":"file","isSymbolicLink":false,"fileMetaData":{"size":10141,"lastModifiedTime":1688461737610}},{"hashValue":"df9cf1f7c2bd8662691cd94da6f49298","name":"OpenHarmonyTestRunner.js.map","path":"D:\\Application\\entry\\build\\default\\intermediates\\loader_out\\ohosTest\\js\\TestRunner\\OpenHarmonyTestRunner.js.map","type":"file","isSymbolicLink":false,"fileMetaData":{"size":2680,"lastModifiedTime":1688461737610}}]}]}]},"D:\\Application\\entry\\build\\default\\intermediates\\assets_jsbundle\\ohosTest\\js":{"hashValue":"6640c7142c1e67060b5a24eaba887d4a","name":"js","path":"D:\\Application\\entry\\build\\default\\intermediates\\assets_jsbundle\\ohosTest\\js","type":"directory","isSymbolicLink":false,"children":[{"hashValue":"04dd2f3ba5335b94ab06d489083a7a24","name":"TestAbility","path":"D:\\Application\\entry\\build\\default\\intermediates\\assets_jsbundle\\ohosTest\\js\\TestAbility","type":"directory","isSymbolicLink":false,"children":[{"hashValue":"86086ff9ee39ef04922b46eaeb427c8d","name":"app.abc","path":"D:\\Application\\entry\\build\\default\\intermediates\\assets_jsbundle\\ohosTest\\js\\TestAbility\\app.abc","type":"file","isSymbolicLink":false,"fileMetaData":{"size":76816,"lastModifiedTime":1688461738574}},{"hashValue":"329aaea2d2e8ed1f88f0666b9a153109","name":"app.js","path":"D:\\Application\\entry\\build\\default\\intermediates\\assets_jsbundle\\ohosTest\\js\\TestAbility\\app.js","type":"file","isSymbolicLink":false,"fileMetaData":{"size":32432,"lastModifiedTime":1688461738461}},{"hashValue":"1fa26a0479cff127e5ce4ad10745fc8a","name":"app.js.map","path":"D:\\Application\\entry\\build\\default\\intermediates\\assets_jsbundle\\ohosTest\\js\\TestAbility\\app.js.map","type":"file","isSymbolicLink":false,"fileMetaData":{"size":16823,"lastModifiedTime":1688461738427}},{"hashValue":"03b29350fdf80f9ee80b41db5ed42f93","name":"i18n","path":"D:\\Application\\entry\\build\\default\\intermediates\\assets_jsbundle\\ohosTest\\js\\TestAbility\\i18n","type":"directory","isSymbolicLink":false,"children":[{"hashValue":"31b44c2273c6b694151084ace0747385","name":"en-US.json","path":"D:\\Application\\entry\\build\\default\\intermediates\\assets_jsbundle\\ohosTest\\js\\TestAbility\\i18n\\en-US.json","type":"file","isSymbolicLink":false,"fileMetaData":{"size":83,"lastModifiedTime":1688461738428}},{"hashValue":"8192745c65142c57ddd31b6b8cb0b7aa","name":"zh-CN.json","path":"D:\\Application\\entry\\build\\default\\intermediates\\assets_jsbundle\\ohosTest\\js\\TestAbility\\i18n\\zh-CN.json","type":"file","isSymbolicLink":false,"fileMetaData":{"size":85,"lastModifiedTime":1688461738427}}]},{"hashValue":"532e7badc2f31e6fabd604c3844e97d7","name":"manifest.json","path":"D:\\Application\\entry\\build\\default\\intermediates\\assets_jsbundle\\ohosTest\\js\\TestAbility\\manifest.json","type":"file","isSymbolicLink":false,"fileMetaData":{"size":256,"lastModifiedTime":1688461738467}},{"hashValue":"c3cad7ce16216ce3b3e47b0950583642","name":"pages","path":"D:\\Application\\entry\\build\\default\\intermediates\\assets_jsbundle\\ohosTest\\js\\TestAbility\\pages","type":"directory","isSymbolicLink":false,"children":[{"hashValue":"6abee471718a361b2b71452f7af76ad0","name":"index","path":"D:\\Application\\entry\\build\\default\\intermediates\\assets_jsbundle\\ohosTest\\js\\TestAbility\\pages\\index","type":"directory","isSymbolicLink":false,"children":[{"hashValue":"a08b6a4108ecd2bf9fedaca82ab0a7a9","name":"index.abc","path":"D:\\Application\\entry\\build\\default\\intermediates\\assets_jsbundle\\ohosTest\\js\\TestAbility\\pages\\index\\index.abc","type":"file","isSymbolicLink":false,"fileMetaData":{"size":23220,"lastModifiedTime":1688461738569}},{"hashValue":"8fda7d3e71fd5c84ba499854441d6d75","name":"index.js","path":"D:\\Application\\entry\\build\\default\\intermediates\\assets_jsbundle\\ohosTest\\js\\TestAbility\\pages\\index\\index.js","type":"file","isSymbolicLink":false,"fileMetaData":{"size":10850,"lastModifiedTime":1688461738427}},{"hashValue":"8c3252a265bb5033fcf06b3db51e54c0","name":"index.js.map","path":"D:\\Application\\entry\\build\\default\\intermediates\\assets_jsbundle\\ohosTest\\js\\TestAbility\\pages\\index\\index.js.map","type":"file","isSymbolicLink":false,"fileMetaData":{"size":1529,"lastModifiedTime":1688461738428}}]}]},{"hashValue":"c3002cd052fd59226a8c7908464fb67c","name":"vendors.abc","path":"D:\\Application\\entry\\build\\default\\intermediates\\assets_jsbundle\\ohosTest\\js\\TestAbility\\vendors.abc","type":"file","isSymbolicLink":false,"fileMetaData":{"size":441768,"lastModifiedTime":1688461738610}},{"hashValue":"5ea847f7af8e1eccc0aaf4ff7c717cfe","name":"vendors.js","path":"D:\\Application\\entry\\build\\default\\intermediates\\assets_jsbundle\\ohosTest\\js\\TestAbility\\vendors.js","type":"file","isSymbolicLink":false,"fileMetaData":{"size":185511,"lastModifiedTime":1688461738427}},{"hashValue":"c1e7143b09b57b67dc2aa9e5f9c85dd4","name":"vendors.js.map","path":"D:\\Application\\entry\\build\\default\\intermediates\\assets_jsbundle\\ohosTest\\js\\TestAbility\\vendors.js.map","type":"file","isSymbolicLink":false,"fileMetaData":{"size":125504,"lastModifiedTime":1688461738427}}]},{"hashValue":"fdd2f79b68e8421134492f6a557e9c57","name":"TestRunner","path":"D:\\Application\\entry\\build\\default\\intermediates\\assets_jsbundle\\ohosTest\\js\\TestRunner","type":"directory","isSymbolicLink":false,"children":[{"hashValue":"0e512e97f1b7d41dc8b3e962c6b6f339","name":"OpenHarmonyTestRunner.abc","path":"D:\\Application\\entry\\build\\default\\intermediates\\assets_jsbundle\\ohosTest\\js\\TestRunner\\OpenHarmonyTestRunner.abc","type":"file","isSymbolicLink":false,"fileMetaData":{"size":22916,"lastModifiedTime":1688461737683}},{"hashValue":"eaff65eb285e9fc32c73ae07a40550ec","name":"OpenHarmonyTestRunner.js","path":"D:\\Application\\entry\\build\\default\\intermediates\\assets_jsbundle\\ohosTest\\js\\TestRunner\\OpenHarmonyTestRunner.js","type":"file","isSymbolicLink":false,"fileMetaData":{"size":10141,"lastModifiedTime":1688461737610}},{"hashValue":"df9cf1f7c2bd8662691cd94da6f49298","name":"OpenHarmonyTestRunner.js.map","path":"D:\\Application\\entry\\build\\default\\intermediates\\assets_jsbundle\\ohosTest\\js\\TestRunner\\OpenHarmonyTestRunner.js.map","type":"file","isSymbolicLink":false,"fileMetaData":{"size":2680,"lastModifiedTime":1688461737610}}]}]},"D:\\Application\\entry\\build\\default\\intermediates\\assets_jsbundle\\ohosTest":{"hashValue":"e8ebb4be018f2cc14a1da15218e55e33","name":"ohosTest","path":"D:\\Application\\entry\\build\\default\\intermediates\\assets_jsbundle\\ohosTest","type":"directory","isSymbolicLink":false,"children":[{"hashValue":"6640c7142c1e67060b5a24eaba887d4a","name":"js","path":"D:\\Application\\entry\\build\\default\\intermediates\\assets_jsbundle\\ohosTest\\js","type":"directory","isSymbolicLink":false,"children":[{"hashValue":"04dd2f3ba5335b94ab06d489083a7a24","name":"TestAbility","path":"D:\\Application\\entry\\build\\default\\intermediates\\assets_jsbundle\\ohosTest\\js\\TestAbility","type":"directory","isSymbolicLink":false,"children":[{"hashValue":"86086ff9ee39ef04922b46eaeb427c8d","name":"app.abc","path":"D:\\Application\\entry\\build\\default\\intermediates\\assets_jsbundle\\ohosTest\\js\\TestAbility\\app.abc","type":"file","isSymbolicLink":false,"fileMetaData":{"size":76816,"lastModifiedTime":1688461738574}},{"hashValue":"329aaea2d2e8ed1f88f0666b9a153109","name":"app.js","path":"D:\\Application\\entry\\build\\default\\intermediates\\assets_jsbundle\\ohosTest\\js\\TestAbility\\app.js","type":"file","isSymbolicLink":false,"fileMetaData":{"size":32432,"lastModifiedTime":1688461738461}},{"hashValue":"1fa26a0479cff127e5ce4ad10745fc8a","name":"app.js.map","path":"D:\\Application\\entry\\build\\default\\intermediates\\assets_jsbundle\\ohosTest\\js\\TestAbility\\app.js.map","type":"file","isSymbolicLink":false,"fileMetaData":{"size":16823,"lastModifiedTime":1688461738427}},{"hashValue":"03b29350fdf80f9ee80b41db5ed42f93","name":"i18n","path":"D:\\Application\\entry\\build\\default\\intermediates\\assets_jsbundle\\ohosTest\\js\\TestAbility\\i18n","type":"directory","isSymbolicLink":false,"children":[{"hashValue":"31b44c2273c6b694151084ace0747385","name":"en-US.json","path":"D:\\Application\\entry\\build\\default\\intermediates\\assets_jsbundle\\ohosTest\\js\\TestAbility\\i18n\\en-US.json","type":"file","isSymbolicLink":false,"fileMetaData":{"size":83,"lastModifiedTime":1688461738428}},{"hashValue":"8192745c65142c57ddd31b6b8cb0b7aa","name":"zh-CN.json","path":"D:\\Application\\entry\\build\\default\\intermediates\\assets_jsbundle\\ohosTest\\js\\TestAbility\\i18n\\zh-CN.json","type":"file","isSymbolicLink":false,"fileMetaData":{"size":85,"lastModifiedTime":1688461738427}}]},{"hashValue":"532e7badc2f31e6fabd604c3844e97d7","name":"manifest.json","path":"D:\\Application\\entry\\build\\default\\intermediates\\assets_jsbundle\\ohosTest\\js\\TestAbility\\manifest.json","type":"file","isSymbolicLink":false,"fileMetaData":{"size":256,"lastModifiedTime":1688461738467}},{"hashValue":"c3cad7ce16216ce3b3e47b0950583642","name":"pages","path":"D:\\Application\\entry\\build\\default\\intermediates\\assets_jsbundle\\ohosTest\\js\\TestAbility\\pages","type":"directory","isSymbolicLink":false,"children":[{"hashValue":"6abee471718a361b2b71452f7af76ad0","name":"index","path":"D:\\Application\\entry\\build\\default\\intermediates\\assets_jsbundle\\ohosTest\\js\\TestAbility\\pages\\index","type":"directory","isSymbolicLink":false,"children":[{"hashValue":"a08b6a4108ecd2bf9fedaca82ab0a7a9","name":"index.abc","path":"D:\\Application\\entry\\build\\default\\intermediates\\assets_jsbundle\\ohosTest\\js\\TestAbility\\pages\\index\\index.abc","type":"file","isSymbolicLink":false,"fileMetaData":{"size":23220,"lastModifiedTime":1688461738569}},{"hashValue":"8fda7d3e71fd5c84ba499854441d6d75","name":"index.js","path":"D:\\Application\\entry\\build\\default\\intermediates\\assets_jsbundle\\ohosTest\\js\\TestAbility\\pages\\index\\index.js","type":"file","isSymbolicLink":false,"fileMetaData":{"size":10850,"lastModifiedTime":1688461738427}},{"hashValue":"8c3252a265bb5033fcf06b3db51e54c0","name":"index.js.map","path":"D:\\Application\\entry\\build\\default\\intermediates\\assets_jsbundle\\ohosTest\\js\\TestAbility\\pages\\index\\index.js.map","type":"file","isSymbolicLink":false,"fileMetaData":{"size":1529,"lastModifiedTime":1688461738428}}]}]},{"hashValue":"c3002cd052fd59226a8c7908464fb67c","name":"vendors.abc","path":"D:\\Application\\entry\\build\\default\\intermediates\\assets_jsbundle\\ohosTest\\js\\TestAbility\\vendors.abc","type":"file","isSymbolicLink":false,"fileMetaData":{"size":441768,"lastModifiedTime":1688461738610}},{"hashValue":"5ea847f7af8e1eccc0aaf4ff7c717cfe","name":"vendors.js","path":"D:\\Application\\entry\\build\\default\\intermediates\\assets_jsbundle\\ohosTest\\js\\TestAbility\\vendors.js","type":"file","isSymbolicLink":false,"fileMetaData":{"size":185511,"lastModifiedTime":1688461738427}},{"hashValue":"c1e7143b09b57b67dc2aa9e5f9c85dd4","name":"vendors.js.map","path":"D:\\Application\\entry\\build\\default\\intermediates\\assets_jsbundle\\ohosTest\\js\\TestAbility\\vendors.js.map","type":"file","isSymbolicLink":false,"fileMetaData":{"size":125504,"lastModifiedTime":1688461738427}}]},{"hashValue":"fdd2f79b68e8421134492f6a557e9c57","name":"TestRunner","path":"D:\\Application\\entry\\build\\default\\intermediates\\assets_jsbundle\\ohosTest\\js\\TestRunner","type":"directory","isSymbolicLink":false,"children":[{"hashValue":"0e512e97f1b7d41dc8b3e962c6b6f339","name":"OpenHarmonyTestRunner.abc","path":"D:\\Application\\entry\\build\\default\\intermediates\\assets_jsbundle\\ohosTest\\js\\TestRunner\\OpenHarmonyTestRunner.abc","type":"file","isSymbolicLink":false,"fileMetaData":{"size":22916,"lastModifiedTime":1688461737683}},{"hashValue":"eaff65eb285e9fc32c73ae07a40550ec","name":"OpenHarmonyTestRunner.js","path":"D:\\Application\\entry\\build\\default\\intermediates\\assets_jsbundle\\ohosTest\\js\\TestRunner\\OpenHarmonyTestRunner.js","type":"file","isSymbolicLink":false,"fileMetaData":{"size":10141,"lastModifiedTime":1688461737610}},{"hashValue":"df9cf1f7c2bd8662691cd94da6f49298","name":"OpenHarmonyTestRunner.js.map","path":"D:\\Application\\entry\\build\\default\\intermediates\\assets_jsbundle\\ohosTest\\js\\TestRunner\\OpenHarmonyTestRunner.js.map","type":"file","isSymbolicLink":false,"fileMetaData":{"size":2680,"lastModifiedTime":1688461737610}}]}]}]},"D:\\Application\\entry\\build\\default\\intermediates\\res\\ohosTest\\config.json":{"hashValue":"3c20b9a05a10977ee66ff48b576e412c","name":"config.json","path":"D:\\Application\\entry\\build\\default\\intermediates\\res\\ohosTest\\config.json","type":"file","isSymbolicLink":false,"fileMetaData":{"size":2900,"lastModifiedTime":1688461735001}},"D:\\Application\\entry\\build\\default\\intermediates\\res\\ohosTest\\resources":{"hashValue":"f21d9664024ebbb34940df857a636a01","name":"resources","path":"D:\\Application\\entry\\build\\default\\intermediates\\res\\ohosTest\\resources","type":"directory","isSymbolicLink":false,"children":[{"hashValue":"6bf07c2c8afe5e472d7486bf4c901722","name":"base","path":"D:\\Application\\entry\\build\\default\\intermediates\\res\\ohosTest\\resources\\base","type":"directory","isSymbolicLink":false,"children":[{"hashValue":"15ad28015a4943708fccc514d361fcbc","name":"media","path":"D:\\Application\\entry\\build\\default\\intermediates\\res\\ohosTest\\resources\\base\\media","type":"directory","isSymbolicLink":false,"children":[{"hashValue":"a75f510daf2a968450be3733ebfd450c","name":"icon.png","path":"D:\\Application\\entry\\build\\default\\intermediates\\res\\ohosTest\\resources\\base\\media\\icon.png","type":"file","isSymbolicLink":false,"fileMetaData":{"size":6790,"lastModifiedTime":1688438694095}}]},{"hashValue":"7654f74531ded4f7df5ebdb776c437a1","name":"profile","path":"D:\\Application\\entry\\build\\default\\intermediates\\res\\ohosTest\\resources\\base\\profile","type":"directory","isSymbolicLink":false,"children":[{"hashValue":"2e5732a0b96269dce11fc2419ce5e783","name":"test_pages.json","path":"D:\\Application\\entry\\build\\default\\intermediates\\res\\ohosTest\\resources\\base\\profile\\test_pages.json","type":"file","isSymbolicLink":false,"fileMetaData":{"size":49,"lastModifiedTime":1688438694102}}]}]}]},"D:\\Application\\entry\\build\\default\\intermediates\\res\\ohosTest\\resources.index":{"hashValue":"b29b7e69dcda743c0abad604c9ab3982","name":"resources.index","path":"D:\\Application\\entry\\build\\default\\intermediates\\res\\ohosTest\\resources.index","type":"file","isSymbolicLink":false,"fileMetaData":{"size":422,"lastModifiedTime":1688461735001}},"D:\\Application\\entry\\build\\default\\outputs\\ohosTest\\entry-ohosTest-unsigned.hap":{"hashValue":"1f971581462487a29bb988f7a9556a58","name":"entry-ohosTest-unsigned.hap","path":"D:\\Application\\entry\\build\\default\\outputs\\ohosTest\\entry-ohosTest-unsigned.hap","type":"file","isSymbolicLink":false,"fileMetaData":{"size":963568,"lastModifiedTime":1688461740746}},"D:\\Application\\entry\\build\\default\\outputs\\ohosTest\\entry-ohosTest-signed.hap":{"hashValue":"86d276673aa765784745f0d60e4e49e9","name":"entry-ohosTest-signed.hap","path":"D:\\Application\\entry\\build\\default\\outputs\\ohosTest\\entry-ohosTest-signed.hap","type":"file","isSymbolicLink":false,"fileMetaData":{"size":968266,"lastModifiedTime":1688461743048}}}