{"subsystem_ch": "\u5168\u7403\u5316\u5b50\u7cfb\u7edf", "subsystem_en": "global", "api_module_name": "D:\\WORK\\NEW_SDK_package_0329\\interface_sdk-js-master\\api\\@system.configuration", "api": [{"api_class_name": "LocaleResponse", "api_method_all": "export interface LocaleResponse {\n  \n  language: string;\n\n  \n  countryOrRegion: string;\n\n  \n  dir: \"ltr\" | \"rtl\";\n}", "api_method_name": "LocaleResponse", "api_type": "", "api_level": 20, "api_args_count": 0, "api_used_count": 0, "since": 3, "api_used": "\u5426", "lines": [], "files": [], "is_white": " ", "desc": " "}, {"api_class_name": "LocaleResponse", "api_method_name": "language", "api_method_all": "language: string", "api_type": "", "api_args_count": 1, "api_level": 22, "api_used_count": 136, "since": 3, "api_used": "\u662f", "lines": ["      expect(locale.language).assertEqual('en');", "'i18n_test_preferredlanguage_0200 ' + 'start');\n", "'i18n_test_preferredlanguage_restoreLang ' + rem", "'i18n_test_preferredlanguage_0200 ' + value);\n  ", "'i18n_test_preferredlanguage_clearLang ' + I18n.", "      expect(locale.language).assertEqual('ja');", "'i18n_test_preferredlanguage_clearLang ' + par);", "'i18n_test_preferredlanguage_restoreLang ' + val", "'i18n_test_preferredlanguage_0100 ' + value);\n  ", "'i18n_test_preferredlanguage_afterEach ' + currL", "'i18n_test_preferredlanguage_0100', 0, function ", "'i18n_test_preferredlanguage_clearLang ' + len);", "est_0200 ' + locale.language);\n        expect(lo", "est_0100 ' + locale.language);\n        expect(lo", "'i18n_test_preferredlanguage_0200 ' + list);\n   ", "'i18n_test_preferredlanguage_0100 ' + 'start');\n", "'i18n_test_preferredlanguage_beforeEach ' + getC", "'i18n_test_preferredlanguage_0220', 0, function ", "'i18n_test_preferredlanguage_restoreLang ' + I18", "'i18n_test_preferredlanguage_0220 ' + value);\n  ", " @tc.desc check the language\n    */\n    it('i18n", "'i18n_test_preferredlanguage_0220 ' + 'start');\n", "'i18n_test_preferredlanguage_0200', 0, function ", "'i18n_test_preferredlanguage_clearLang ' + value"], "files": ["I18n.test.js", "Lang.test.js", "Perf.test.js", "Intl.test.js"], "is_white": " ", "desc": " "}, {"api_class_name": "LocaleResponse", "api_method_name": "countryOrRegion", "api_method_all": "countryOrRegion: string", "api_type": "", "api_args_count": 1, "api_level": 22, "api_used_count": 0, "since": 3, "api_used": "\u5426", "lines": [], "files": [], "is_white": " ", "desc": " "}, {"api_class_name": "LocaleResponse", "api_method_name": "dir", "api_method_all": "dir: \"ltr\" | \"rtl\"", "api_type": "", "api_args_count": 1, "api_level": 22, "api_used_count": 2, "since": 3, "api_used": "\u662f", "lines": ["                cfg.direction = Direction.D"], "files": ["Resmgr.test.js"], "is_white": " ", "desc": " "}, {"api_class_name": "Configuration", "api_method_all": "export default class Configuration {\n  \n  static getLocale(): LocaleResponse;\n}", "api_method_name": "Configuration", "api_type": "", "api_level": 10, "api_args_count": 0, "api_used_count": 4, "since": 3, "api_used": "\u662f", "lines": ["})\n\n    \n    it('getConfiguration_test_001', 0, async", "})\n\n    \n    it('getConfiguration_test_002', 0, async", "\n            mgr.getConfiguration((error, cfg) => {\n ", "\n            mgr.getConfiguration().then(cfg => {\n   "], "files": ["Resmgr.test.js"], "is_white": " ", "desc": " "}, {"api_class_name": "Configuration", "api_method_name": "getLocale", "api_method_all": "static getLocale(): LocaleResponse;", "api_type": "", "api_args_count": 0, "api_level": 11, "api_used_count": 0, "since": 0, "api_used": "\u5426", "lines": [], "files": [], "is_white": " ", "desc": " "}]}