{"subsystem_ch": "ACE\u5f00\u53d1\u6846\u67b6", "subsystem_en": "ace", "api_module_name": "D:\\WORK\\NEW_SDK_package_0329\\interface_sdk-js-master\\api\\@internal\\component\\ets\\rating", "api": [{"api_class_name": "RatingInterface", "api_method_all": "interface RatingInterface {\n  \n  (options?: { rating: number; indicator?: boolean }): RatingAttribute;\n}", "api_method_name": "RatingInterface", "api_type": "", "api_level": 20, "api_args_count": 0, "api_used_count": 0, "since": 7, "api_used": "\u5426", "lines": [], "files": [], "is_white": " ", "desc": " "}, {"api_class_name": "RatingInterface", "api_method_name": "options", "api_method_all": "(options?: { rating: number", "api_type": "", "api_args_count": 1, "api_level": 22, "api_used_count": 791, "since": 7, "api_used": "\u662f", "lines": ["= await router.push(options);\n          await U", " start\");\n      let options = {\n        uri: 'p", "(obj.$attrs.overlay.options.offset.x).assertEqu", "(obj.$attrs.overlay.options.align).assertEqual(", "(obj.$attrs.overlay.options.offset.y).assertEqu", " (done) {\n      let options = {\n        uri: 'p"], "files": ["listItemGroupProps.test.js", "ImageJsunit.test.ets", "RowSplitJsunit.test.ets", "pathProps.test.js", "CounterJsunit.test.ets", "dividerProps.test.js", "ImageEffectsJsunit.test.ets", "ListItemJsunit.test.ets", "tabContentProps.test.js", "textProps.test.js", "DragEventJsunit.test.ets", "ParallelGestureJsunit.test.ets", "ScrollBarJsunit.test.ets", "toolbarProps.test.js", "ColumnSplitJsunit.test.ets", "TextPickerJsunit.test.ets", "PolygonJsunit.test.ets", "TouchAbleJsunit.test.ets", "ZIndexJsunit.test.ets", "PathJsunit.test.ets", "polylineProps.test.js", "CheckboxGroupJsunit.test.ets", "PositionSettingJsunit.test.ets", "searchProps.test.js", "spanProps.test.js", "TextStyleJsunit.test.ets", "toolbarItemProps.test.js", "OhosRouterJsnuit.test.ets", "AppearJsunit.test.ets", "TapGesture.test.ets", "TextClockJsunit.test.ets", "PieceJsunit.test.ets", "PlacementJsunit.test.ets", "PolylineJsunit.test.ets", "GeometryTransitionJsunit.test.ets", "OverlayJsunit.test.ets", "LineJsunit.test.ets", "ScrollCodeJsunit.test.ets", "DividerJsunit.test.ets", "badgeProps.test.js", "basicabilityapi.test.js", "PriorityGestureJsunit.test.ets", "RichTextJsunit.test.ets", "FillModeJsunit.test.ets", "dialogProps.test.js", "CalendarJsunit.test.ets", "TouchJsunit.test.ets", "LongPressGesture.test.ets", "LinkJsunit.test.ets", "NavigatorCodeJsunit.test.ets", "EllipseJsunit.test.ets", "GridJsnuit.test.ets", "CurvesJsunit.test.ets", "FlexWrapJsunit.test.ets", "formProps.test.js", "VideoJsunit.test.ets", "SelectJsunit.test.ets", "DirectionJsunit.test.ets", "circleProps.test.js", "EnmusFlexAlignJsunit.test.ets", "SourceTypeJsunit.test.ets", "PanDirectionJsunit.test.ets", "RadioJsunit.test.ets", "stackProps.test.js", "SpanJsunit.test.ets", "EdgeEffectJsunit.test.ets", "StepperJsunit.test.ets", "PanelJsunit.test.ets", "ButtonJsunit.test.ets", "PanGestureJsunit.test.ets", "TextJsunit.test.ets", "LayoutConstraintsJsunit.test.ets", "GridJsunit.test.ets", "refreshProps.test.js", "ScrollerBarJsunit.test.ets", "EnmusItemAlignJsunit.test.ets", "EnmusImageJsunit.test.ets", "GridContainerJsunit.test.ets", "TransitionJsunit.test.ets", "SearchJsunit.test.ets", "EnmusHorizontalAlignJsunit.test.ets", "AreaChangeJsunit.test.ets", "VisibilityJsunit.test.ets", "canvasProps.test.js", "AnimateJsunit.test.ets", "BlankJsunit.test.ets", "RefreshJsunit.test.ets", "ResponseRegionJsunit.test.ets", "animatorOption.ets", "PropJsunit.test.ets", "FlexJsunit.test.ets", "QrCodeJsunit.test.ets", "AppStorageJsunit.test.ets", "ProgressJsunit.test.ets", "TimeStampJsunit.test.ets", "GridItem.test.ets", "richtextProps.test.js", "svgProps.test.js", "labelProps.test.js", "Canvas2Jsunit.test.ets", "svgTextProps.test.js", "textPathProps.test.js", "ListJsunit.test.ets", "FlexDirectionJsunit.test.ets", "gridContainerProps.test.js", "ColorGradientJsunit.test.ets", "ratingProps.test.js", "stepperProps.test.js", "MotionPathJsunit.test.ets", "marqueeProps.test.js", "imageAnimatorProps.test.js", "ShapeJsunit.test.ets", "tabsProps.test.js", "qrcodeProps.test.js", "lineProps.test.js", "GlobalJsunit.test.ets", "popupProps.test.js", "ToggleJsunit.test.ets", "SystemRouterJsunit.test.ets", "OhosPromptJsunit.test.ets", "listItemProps.test.js", "ConfigurationJsunit.test.ets", "PatternLockJsunit.test.ets", "gridRowProps.test.js", "stepperItemProps.test.js", "videoProps.test.js", "BindMenuJsunit.test.ets", "EnmusVerticalAlignJsunit.test.ets", "MarqueeJsunit.test.ets", "BackgroundJsunit.test.ets", "DatePickerJsunit.test.ets", "GaugeJsunit.test.ets", "optionProps.test.js", "PageTransitionJsunit.test.ets", "TextInputJsunit.test.ets", "AlphabetIndexerJsunit.test.ets", "animateTransformProps.test.js", "DataPanelJsunit.test.ets", "QrcodeJsunit.test.ets", "pieceProps.test.js", "TextAreaJsunit.test.ets", "StackJsunit.test.ets", "pickerProps.test.js", "animateMotionProps.test.js", "selectProps.test.js", "CustomDialogControllerJsunit.test.ets", "ScrollJsunit.test.ets", "textareaProps.test.js", "gridColProps.test.js", "buttonProps.test.js", "animateProps.test.js", "BackgroundAndSizeSettingJsunit.test.ets", "AnimationStatusJsunit.test.ets", "BorderJsunit.test.ets", "EnmusLineCapStyleJsunit.test.ets", "OhosMatrix4Jsunit.test.ets", "EnableJsunit.test.ets", "BadgeJsunit.test.ets", "AboutToDisappearJsunit.test.ets", "pickerViewProps.test.js", "CircleJsunit.test.ets", "divProps.test.js", "switchProps.test.js", "FocusJsunit.test.ets", "PlayModeJsunit.test.ets", "ImageAnimatorJsunit.test.ets", "GradientDirectionJsunit.test.ets", "commonComponentJsApi.test.js", "ellipseProps.test.js", "TransFormJsunit.test.ets", "GestureModeJsunit.test.ets", "chartProps.test.js", "SliderJsunit.test.ets", "SharedTransitionJsunit.test.ets", "CanvasJsunit.test.ets", "CheckboxJsunit.test.ets", "sliderProps.test.js", "swiperProps.test.js", "TextTimerJsunit.test.ets", "SystempromptJsunit.test.ets", "NavigatorJsunit.test.ets", "TabsJsunit.test.ets", "polygonProps.test.js", "LoadingProgressJsunit.test.ets", "RowJsunit.test.ets", "TabJsunit.test.ets", "ShapeClippingJsunit.test.ets", "inputProps.test.js", "GridSettingsJsunit.test.ets", "index.js", "tabBarProps.test.js", "SwiperJsunit.test.ets", "toggleProps.test.js", "ColumnJsunit.test.ets", "tspanProps.test.js", "imageProps.test.js", "listProps.test.js", "progressProps.test.js", "NavigationJsunit.test.ets", "RatingJsunit.test.ets", "Direction2Jsunit.test.ets", "panelProps.test.js", "BindPopupJsunit.test.ets", "menuProps.test.js", "rectProps.test.js"], "is_white": " ", "desc": " "}, {"api_class_name": "RatingInterface", "api_method_name": "indicator", "api_method_all": "indicator?: boolean }): RatingAttribute", "api_type": "", "api_args_count": 1, "api_level": 22, "api_used_count": 111, "since": 7, "api_used": "\u662f", "lines": ["ne = this.$element(\"indicatorNone\").getInspector(", "alse: null,\n        indicatorMaskPropTrue: null,\n", "ctor()\n        this.indicatorTrue = this.$element", "ctor()\n        this.indicatorNone = this.$element", "rue : null,\n        indicatorNone : null\n    },\n\n", "Prop: null,\n        indicatorPropTrue: null,\n    ", "ating: this.rating, indicator: this.indicator })\n", "ng, indicator: this.indicator })\n        .stars(5", "alProp,\n            indicatorPropTrue: this.indic", ".edgeEffect)\n      .indicatorStyle({ top: 20, rig", "  expect(obj.$attrs.indicator).assertEqual(\"true\"", "  expect(obj.$attrs.indicator).assertEqual('true'", "xpect(objNew.$attrs.indicator).assertEqual('false", "nsole.info(\"rating2 indicator\" + JSON.stringify(o", "True: null,\n        indicatorDisabledPropFalse: n", "alse: null,\n        indicatorDisabledPropTrue: nu", "True: null,\n        indicatorMaskPropFalse: null,", "tringify(obj.$attrs.indicator))\n      expect(obj.", "Rating({ rating: 2, indicator: false })\n         ", "rFalse,\n            indicatorTrue : this.indicato", "ndicatorTrue : this.indicatorTrue,\n            in", "True: null,\n        indicatorPropFalse: null,\n   ", "ctor()\n        this.indicatorFalse = this.$elemen", "nsole.log('Swiper\u2018s indicator is ' + JSON.stringi", "ber = 4000\n  @State indicator: boolean = true\n  @", "ata: {\n            \"indicator\": \"false\"\n         ", "tringify(obj.$attrs.indicator))\n      console.log", "tringify(obj.$attrs.indicator))\n      console.inf", "ue = this.$element(\"indicatorTrue\").getInspector(", "lse : null,\n        indicatorTrue : null,\n       ", "ndicatorNone : this.indicatorNone\n        }\n    }", "is.interval)\n      .indicator(this.indicator)\n   ", "ize : null,\n        indicatorFalse : null,\n      ", "number = 1\n  @State indicator: boolean = false\n  ", "epsize,\n            indicatorFalse : this.indicat", "yle: \" + obj.$attrs.indicatorStyle);\n      expect", "se = this.$element(\"indicatorFalse\").getInspector", "catorPropTrue: this.indicatorPropTrue,\n          ", "est_0100 obj.$attrs.indicatorStyle: \" + obj.$attr", "    .indicator(this.indicator)\n      .loop(this.l", "Rating({ rating: 2, indicator: true })\n          ", "dicatorFalse : this.indicatorFalse,\n            i", "  expect(obj.$attrs.indicator).assertEqual(\"false", " if (eventData.data.indicator != null) {\n        ", "nsole.info(\"rating1 indicator\" + JSON.stringify(o", "orTrue,\n            indicatorNone : this.indicato", "or = eventData.data.indicator;\n      }\n      if (", "ull) {\n        this.indicator = eventData.data.in", "terval(4000)\n      .indicator(true)\n      .loop(f"], "files": ["ratingProps.test.js", "swiperProps.test.js", "swiper.ets", "RatingJsunit.test.ets", "Rating.ets", "rating.ets", "index.js", "SwiperJsunit.test.ets", "Swiper.ets"], "is_white": " ", "desc": " "}, {"api_class_name": "RatingAttribute", "api_method_all": "declare class RatingAttribute extends CommonMethod<RatingAttribute> {\n  \n  stars(value: number): RatingAttribute;\n\n  \n  stepSize(value: number): RatingAttribute;\n\n  \n  starStyle(value: { backgroundUri: string; foregroundUri: string; secondaryUri?: string }): RatingAttribute;\n\n  \n  onChange(callback: (value: number) => void): RatingAttribute;\n}", "api_method_name": "RatingAttribute", "api_type": "", "api_level": null, "api_args_count": 0, "api_used_count": 0, "since": 0, "api_used": "\u5426", "lines": [], "files": [], "is_white": " ", "desc": " "}, {"api_class_name": "RatingAttribute", "api_method_name": "stars", "api_method_all": "stars(value: number): RatingAttribute;", "api_type": "", "api_args_count": 1, "api_level": null, "api_used_count": 17, "since": 7, "api_used": "\u662f", "lines": ["(){\n        this.numstars = this.$element(\"nu", "= this.$element(\"numstars\").getInspector()\n  ", "   it('testRatingNumstars', 0, async function", "nsole.info(\"rating1 stars\" + JSON.stringify(o", "ize(0.5)\n          .stars(5)\n          .starS", "tringify(obj.$attrs.stars))\n      console.inf", "id).assertEqual('numstars')\n        expect(ob", ".info('testRatingNumstars START');\n        co", "ne,\n\n            numstars : this.numstars,\n  ", "dicator })\n        .stars(5).key('Rating')\n  ", "globalThis.value.numstars);\n        console.i", " numstars : this.numstars,\n            rating", ": null,\n\n        numstars : null,\n        rat", "  expect(obj.$attrs.stars).assertEqual(\"5\")\n ", "e      testRatingNumstars\n     * @tc.desc    ", "xpect(obj.$attrs.numstars).assertEqual('5')\n "], "files": ["ratingProps.test.js", "RatingJsunit.test.ets", "Rating.ets", "rating.ets", "index.js"], "is_white": " ", "desc": " "}, {"api_class_name": "RatingAttribute", "api_method_name": "stepSize", "api_method_all": "stepSize(value: number): RatingAttribute;", "api_type": "", "api_args_count": 1, "api_level": null, "api_used_count": 7, "since": 7, "api_used": "\u662f", "lines": ["nsole.info(\"rating1 stepSize\" + JSON.stringify(o", "('Rating')\n        .stepSize(0.5)\n        .onCha", "false })\n          .stepSize(0.5)\n          .sta", " true })\n          .stepSize(0.5)\n          .sta", "  expect(obj.$attrs.stepSize).assertEqual(\"0.500", "tringify(obj.$attrs.stepSize))\n      console.inf"], "files": ["RatingJsunit.test.ets", "rating.ets", "Rating.ets"], "is_white": " ", "desc": " "}, {"api_class_name": "RatingAttribute", "api_method_name": "starStyle", "api_method_all": "starStyle(value: { backgroundUri: string; foregroundUri: string; secondaryUri?: string }): RatingAttribute;", "api_type": "", "api_args_count": 1, "api_level": null, "api_used_count": 5, "since": 7, "api_used": "\u662f", "lines": ["tringify(obj.$attrs.starStyle))\n      expect(obj.", "nsole.info(\"rating1 starStyle\" + JSON.stringify(o", "stars(5)\n          .starStyle({\n            backg", "  expect(obj.$attrs.starStyle)\n        .assertEqu"], "files": ["RatingJsunit.test.ets", "Rating.ets"], "is_white": " ", "desc": " "}, {"api_class_name": "RatingAttribute", "api_method_name": "onChangecallback", "api_method_all": "onChange(callback: (value: number) => void): RatingAttribute;", "api_type": "callback", "api_args_count": 2, "api_level": null, "api_used_count": 0, "since": 0, "api_used": "\u5426", "lines": [], "files": [], "is_white": " ", "desc": " "}, {"api_class_name": "RatingAttribute", "api_method_name": "onChangecallback", "api_method_all": "onChange(callback: (value: number) => void): RatingAttribute;", "api_type": "callback", "api_args_count": 2, "api_level": null, "api_used_count": 0, "since": 0, "api_used": "\u5426", "lines": [], "files": [], "is_white": " ", "desc": " "}]}